Workbook
Name _Order1: 255
Name _Order2: 255
Name AccessDatabase: "D:\Nuevos Cursos\Excel\Presupuesto y control presupuestario.mdb"
Name AMPO5: "Gráfico 8"
Name cuadro17: {"'ExpoBR'!$B$2:$N$29"}
Name daniela: {"'TCM IPM Urug'!$A$6:$N$20"}
Name dw: {"3",#N/A,FALSE,"BASE MONETARIA";"4",#N/A,FALSE,"BASE MONETARIA"}
Name h: {"3",#N/A,FALSE,"BASE MONETARIA";"4",#N/A,FALSE,"BASE MONETARIA"}
Name HTML_CodePage: 1252
Name HTML_Control: {"'TCM IPM Urug'!$A$6:$N$20"}
Name HTML_Description: ""
Name HTML_Email: ""
Name HTML_Header: "TCM IPM Urug"
Name HTML_LastUpdate: "15/06/2001"
Name HTML_LineAfter: FALSE()
Name HTML_LineBefore: FALSE()
Name HTML_Name: "Iga"
Name HTML_OBDlg2: TRUE()
Name HTML_OBDlg4: TRUE()
Name HTML_OS: 0
Name HTML_PathFile: "C:\Mis documentos\anexos mercosur mayo de 2001\tipo de cambio RM uruguay.htm"
Name HTML_Title: "anemer2 pdf(7 de junio de 2001)"
Name wrn.BMA.: {"3",#N/A,FALSE,"BASE MONETARIA";"4",#N/A,FALSE,"BASE MONETARIA"}
Name wrn.PASMON.: {"1",#N/A,FALSE,"Pasivos Mon";"2",#N/A,FALSE,"Pasivos Mon"}
Name x: {"'ExpoBR'!$B$2:$N$29"}

Sheet CONTROL
B2: TIR Nominal (con IVA) | C2: =+FLUJO!$C$49 -> 2.2128475
B3: TIR Modificada | C3: =IF(C12=2,MIRR(FLUJO!C45:V45,G26,G21),MIRR(FLUJO!C45:Q45,G26,G21)) -> 0.17243491
B4: VAN | C4: =+FLUJO!$C$51 -> 4.4958838e+10
B5: (VAFF / VAE) | C5: =+FLUJO!C54 -> 0.14937691
B6: PAYBACK en Años (flujo acumulado positivo) | C6: =+FLUJO!C60 -> 10
B9: HIPOTESIS OPERATIVAS | E9: HIPOTESIS FINANCIERAS | N9: CHECKS
B11: Fechas | E11: Egresos Totales (sin IVA) | F11: % | I11: Ingresos Totales (sin IVA) | K11: % | N11: Errores | O11: =+COUNTIF(O12:O21,"*Error*") -> 0
B12: Escenario Plazos | C12: 2 | E12: Obras | F12: =+G12/$G$18 -> 0.16136537 | G12: =+SUM(FLUJO!C36:V37) -> 113012430000 | I12: Ingresos por Peajes | K12: =+L12/$L$14 -> 0.97418119 | L12: =+SUM(FLUJO!C19:V20) -> 8.8044542e+11 | N12: Check Payout | O12: =+IF(AND(C12=1,C6>=15)," Error "," OK ") -> OK
A13: 15 | B13: Escenario 15 años | C13: 1 | E13: Repavimentaciones | F13: =+G13/$G$18 -> 0.17181776 | G13: =+SUM(FLUJO!C38:V38) -> 1.2033277e+11 | I13: Disposición de Deuda | K13: =+L13/$L$14 -> 0.025818807 | L13: =+SUM(FLUJO!C21:V21) -> 23334520011 | N13: Total de Cuotas | O13: =+IF(G28>20," Error ", " Ok ") -> Ok
B14: Escenario 20 años | C14: 2 | E14: OPEX | F14: =+G14/$G$18 -> 0.28207967 | G14: =+SUM(FLUJO!C25:V28) -> 197554834820 | I14: Total Origen de fondos | K14: =+SUM(K12:K13) -> 1 | L14: =+SUM(L12:L13) -> 9.0377994e+11 | N14: Tasa de Descuento VAN | O14: =+IF(G21<G26," Error ", " OK ") -> OK
B15: Toma de Posesión | C15: 46388 | E15: Deuda de Largo Plazo | F15: =+G15/$G$18 -> 0.047966446 | G15: =+SUM(FLUJO!C29:V29) -> 3.3593358e+10 | N15: Check Amortizaciones | O15: =+IF(OR(ABS(AMORTIZACIONES!X48-AMORTIZACIONES!X7-AMORTIZACIONES!X20)>1,ABS(AMORTIZACIONES!X98-AMORTIZACIONES!X57-AMORTIZACIONES!X70)>1,ABS(AMORTIZACIONES!X148-AMORTIZACIONES!X107-AMORTIZACIONES!X120)>1)," Error "," OK ") -> OK
B16: Fin del Contrato | C16: =+IF(C12=2,"diciembre 2046","diciembre 2041") -> diciembre 2046 | E16: Gastos Garantias | F16: =+G16/$G$18 -> 0.0028557101 | G16: =+FLUJO!W41 -> 2000000000 | I16: Variantes de Amortización | L16: 1
E17: Impuestos | F17: =+G17/$G$18 -> 0.33391504 | G17: =+SUM(FLUJO!C30:V30) -> 2.338578e+11 | I17: Obras en 20 años y Rep. en 5 años | L17: 1
B18: Tránsitos (BASE 2026) | E18: Total necesidades de financiación | F18: =+SUM(F12:F17) -> 1 | G18: =+SUM(G12:G17) -> 7.0035119e+11 | I18: Obras y Repavimentaciones en 5 años | L18: 2
B19: UTEQUIS | I19: Instantanea (en el año de ejecución) | L19: 3
C20: 7200000 | E20: Tasa de Descuento para Cálculo de VAN
C21: 0 | D21: <- UTEQUIS peajes adicionales (FLUJO fila 74). Dejar en 0 si no hay. | E21: Tasa de Descuento para Cálculo de VAN | G21: 0.1
B23: Tarifas | E23: Deuda de Largo Plazo
B24: Tarifa | C24: 4680 | E24: Importe del Crédito | G24: =+G25*FLUJO!W97 -> 23334520011
E25: Porcentaje de Deuda sobre Obras+Rep | G25: 0.1
E26: Tasa (TNA) | G26: 0.085
B27: Sensibilidades | E27: Cuota (anual) | G27: =+'PRESTAMO '!D13 -> 5.5600021e+09
B28: Sensibilidad Inversión CAPEX | E28: Total de Cuotas | G28: 6
B29: Obras Obligatorias | C29: 0 | E29: Sistemas de Amortización | G29: 1
B30: Gastos Repavimentación | C30: 0 | E30: Frances | G30: 1
B31: Sensibilidad OPEX | E31: Alemán | G31: 2
B32: Conservación y Mantenimiento | C32: 0 | E32: Año de GRACIA | G32: si
B33: Atención al Usuario | C33: 0
B34: Administración | C34: 0
B35: Explotación | C35: 0
B36: Sensibilidad Incremento del Tránsito Annual | C36: 0.03 | E36: GARANTIA A PRIMER REQUERIMIENTO
B37: Sensibilidad Nuevos Peajes año 2028 (año 2) | C37: 1
B38: Sensibilidad Nuevos Peajes año 2029 (año 3) | C38: 1 | E38: Tipo de Garantía | F38: Monto Garantizado | G38: Costo %
B39: Sensibilidad Nuevos Peajes año 2030 (año 4) | C39: 1 | E39: Contrato (CAPEX) | G39: 0.01
B40: Sensibilidad Nuevos Peajes año 2031 (año 5) | C40: 1 | E40: Obras (OPEX) 1 a 5 años | G40: 0.01
E41: 6 a 20 años
B42: Impuestos
B43: Ingresos Brutos | C43: 0.025 | F43: Costo Anual | G43: Total Concesión
B44: Impuesto a las Ganancias | C44: 0.35 | E44: (CAPEX + OPEX) 1 a 5 años | F44: =+F39*G39+F40*G40 -> 0 | G44: =+F44*5 -> 0
B45: Impuesto al Débito y Crédito Bancario | C45: 0.012 | E45: 6 a 20 años | F45: =+F39*G39+F41*G40 -> 0 | G45: =+F45*15 -> 0
B46: IVA | C46: 0.21
B47: IVA OPEX | C47: 0.11 | E47: POLIZA DE SEGURO DE CAUCIÓN
B48: IVA (Conservación y Mantenimiento) | C48: 0.15
B49: IVA (Atención al Usuario) | C49: 0.08 | E49: Tipo de Garantía | F49: Monto Garantizado | G49: Costo %
B50: IVA (Administración) | C50: 0.057 | E50: Obras | F50: =ROUND(SUM(G12:G13)*0.03,-8) -> 7000000000 | G50: 0.01
B51: IVA (Explotación) | C51: 0.18 | E51: Contrato 1 a 5 años | F51: =ROUND(G14*0.015,-8) -> 3000000000 | G51: 0.01
B52: IVA CAPEX | C52: 0.21 | E52: 6 a 20 años | F52: =F51 -> 3000000000
B53: Impuesto de Sellos | C53: 0.012
B54: Tasas Municipales | C54: 0.005 | F54: Costo Anual | G54: Total Concesión
B55: Porcentaje de la Inversión que se Amortiza | C55: 1 | E55: (CAPEX + OPEX) 1 a 5 años | F55: =+F50*G50+F51*G51 -> 100000000 | G55: =+F55*5 -> 500000000
B56: Porcentaje deducción de Intereses en IIGG | C56: 0.3 | E56: 6 a 20 años | F56: =+F50*G50+F52*G51 -> 100000000 | G56: =+F56*15 -> 1500000000
B57: Vida útil Repavimentación (años) | C57: 5
B58: Vida útil Obras en variante "5 años" (años) | C58: 5

Sheet FLUJO
B2: F L U J O D E F O N D O S P R O Y E C T O
B4: 1 de junio 2026 | C4: =+C69 -> 2027 | D4: =+D69 -> 2028 | E4: =+E69 -> 2029 | F4: =+F69 -> 2030 | G4: =+G69 -> 2031 | H4: =+H69 -> 2032 | I4: =+I69 -> 2033 | J4: =+J69 -> 2034 | ... V4: =+V69 -> 2046
B5: =CONTROL!B2 -> TIR Nominal (con IVA) | C5: =+CONTROL!C15 -> 46388 | D5: =+EDATE(C5,12) -> 46753 | E5: =+EDATE(D5,12) -> 47119 | F5: =+EDATE(E5,12) -> 47484 | G5: =+EDATE(F5,12) -> 47849 | H5: =+EDATE(G5,12) -> 48214 | I5: =+EDATE(H5,12) -> 48580 | J5: =+EDATE(I5,12) -> 48945 | K5: =+EDATE(J5,12) -> 49310 | ... V5: =+EDATE(U5,12) -> 53328
B6: =CONTROL!C2 -> 2.2128475 | C6: =+EDATE(C5,12)-1 -> 46752 | D6: =+EDATE(C6,12) -> 47118 | E6: =+EDATE(D6,12) -> 47483 | F6: =+EDATE(E6,12) -> 47848 | G6: =+EDATE(F6,12) -> 48213 | H6: =+EDATE(G6,12) -> 48579 | I6: =+EDATE(H6,12) -> 48944 | J6: =+EDATE(I6,12) -> 49309 | K6: =+EDATE(J6,12) -> 49674 | ... V6: =+EDATE(U6,12) -> 53692
B8: Año de Concesión | C8: 1 | D8: 2 | E8: 3 | F8: 4 | G8: 5 | H8: 6 | I8: 7 | J8: 8 | K8: 9 | L8: 10 | M8: 11 | N8: 12 | O8: 13 | P8: 14 | Q8: 15 | R8: 16 | S8: 17 | T8: 18 | U8: 19 | V8: 20
B9: Días del Año | C9: =+C6-C5+1 -> 365 | D9: =+D6-D5+1 -> 366 | E9: =+E6-E5+1 -> 365 | F9: =+F6-F5+1 -> 365 | G9: =+G6-G5+1 -> 365 | H9: =+H6-H5+1 -> 366 | I9: =+I6-I5+1 -> 365 | J9: =+J6-J5+1 -> 365 | ... V9: =+V6-V5+1 -> 365
B10: Días del Año (Operación) | C10: =+C9 -> 365 | D10: =+D9 -> 366 | E10: =+E9 -> 365 | F10: =+F9 -> 365 | G10: =+G9 -> 365 | H10: =+H9 -> 366 | I10: =+I9 -> 365 | J10: =+J9 -> 365 | ... V10: =+V9 -> 365
B11: Días del Año (Construcción) | C11: =+C10 -> 365 | D11: =+D10 -> 366 | E11: =+E10 -> 365 | F11: =+F10 -> 365 | G11: =+G10 -> 365 | H11: =+H10 -> 366 | I11: =+I10 -> 365 | J11: =+J10 -> 365 | ... V11: =+V10 -> 365
B12: Factor de Ingresos | C12: =+HIPOTESIS!C11 -> 1 | D12: =+HIPOTESIS!D11 -> 1 | E12: =+HIPOTESIS!E11 -> 1 | F12: =+HIPOTESIS!F11 -> 1 | G12: =+HIPOTESIS!G11 -> 1 | H12: =+HIPOTESIS!H11 -> 1 | I12: =+HIPOTESIS!I11 -> 1 | J12: =+HIPOTESIS!J11 -> 1 | ... V12: =+HIPOTESIS!V11 -> 1
B13: Factor de Operación | C13: =+HIPOTESIS!C12 -> 1 | D13: =+HIPOTESIS!D12 -> 1 | E13: =+HIPOTESIS!E12 -> 1 | F13: =+HIPOTESIS!F12 -> 1 | G13: =+HIPOTESIS!G12 -> 1 | H13: =+HIPOTESIS!H12 -> 1 | I13: =+HIPOTESIS!I12 -> 1 | J13: =+HIPOTESIS!J12 -> 1 | ... V13: =+HIPOTESIS!V12 -> 1
B14: Factor de Construcción | C14: =+HIPOTESIS!C13 -> 1 | D14: =+HIPOTESIS!D13 -> 1 | E14: =+HIPOTESIS!E13 -> 1 | F14: =+HIPOTESIS!F13 -> 1 | G14: =+HIPOTESIS!G13 -> 1 | H14: =+HIPOTESIS!H13 -> 1 | I14: =+HIPOTESIS!I13 -> 1 | J14: =+HIPOTESIS!J13 -> 1 | ... V14: =+HIPOTESIS!V13 -> 1
B16: Tránsitos Crecimiento Anual | D16: =CONTROL!C36 -> 0.03 | E16: =+D16 -> 0.03 | F16: =+E16 -> 0.03 | G16: =+F16 -> 0.03 | H16: =+G16 -> 0.03 | I16: =+H16 -> 0.03 | J16: =+I16 -> 0.03 | K16: =+J16 -> 0.03 | L16: =+K16 -> 0.03 | ... V16: =+U16 -> 0.03 | W16: TOTAL
B17: INGRESOS (con IVA)
B18: Ingresos Peajes y Otros | C18: =SUM(C19:C20) -> 0 | D18: =SUM(D19:D21) -> 35053948800 | E18: =SUM(E19:E21) -> 36105567264 | F18: =SUM(F19:F21) -> 3.7188734e+10 | G18: =SUM(G19:G21) -> 3.8304396e+10 | H18: =SUM(H19:H21) -> 3.9453528e+10 | I18: =SUM(I19:I21) -> 4.0637134e+10 | J18: =SUM(J19:J21) -> 4.1856248e+10 | K18: =SUM(K19:K21) -> 4.3111936e+10 | ... Q18: =SUM(Q19:Q21) -> 5.1477906e+10 | R18: =IF(CONTROL!$C$12=2,SUM(R19:R21),0) -> 5.3022243e+10 | S18: =IF(CONTROL!$C$12=2,SUM(S19:S21),0) -> 5.461291e+10 | T18: =IF(CONTROL!$C$12=2,SUM(T19:T21),0) -> 5.6251297e+10 | U18: =IF(CONTROL!$C$12=2,SUM(U19:U21),0) -> 5.7938836e+10 | V18: =IF(CONTROL!$C$12=2,SUM(V19:V21),0) -> 5.9677001e+10 | W18: =+SUM(C18:V18) -> 8.8044542e+11
B19: Peajes | C19: =+C73+C74 -> 0 | D19: =+D73+D74 -> 34706880000 | E19: =+E73+E74 -> 35748086400 | F19: =+F73+F74 -> 36820528992 | G19: =+G73+G74 -> 3.7925145e+10 | H19: =+H73+H74 -> 3.9062899e+10 | I19: =+I73+I74 -> 4.0234786e+10 | J19: =+J73+J74 -> 4.144183e+10 | ... V19: =+V73+V74 -> 5.908614e+10 | W19: =+SUM(C19:V19) -> 8.7172814e+11
B20: Otros Ingresos | C20: =+C75 -> 0 | D20: =+D75 -> 347068800 | E20: =+E75 -> 357480864 | F20: =+F75 -> 3.6820529e+08 | G20: =+G75 -> 3.7925145e+08 | H20: =+H75 -> 3.9062899e+08 | I20: =+I75 -> 4.0234786e+08 | J20: =+J75 -> 4.144183e+08 | ... V20: =+V75 -> 5.908614e+08 | W20: =+SUM(C20:V20) -> 8.7172814e+09
B21: Ingresos Crédito LP | C21: =+C76 -> 23334520011 | D21: =+D76 -> 0 | E21: =+E76 -> 0 | F21: =+F76 -> 0 | G21: =+G76 -> 0 | H21: =+H76 -> 0 | I21: =+I76 -> 0 | J21: =+J76 -> 0 | ... V21: =+V76 -> 0 | W21: =+SUM(C21:V21) -> 23334520011
B22: TOTAL INGRESOS | C22: =SUM(C19:C21) -> 23334520011 | D22: =SUM(D19:D21) -> 35053948800 | E22: =SUM(E19:E21) -> 36105567264 | F22: =SUM(F19:F21) -> 3.7188734e+10 | G22: =SUM(G19:G21) -> 3.8304396e+10 | H22: =SUM(H19:H21) -> 3.9453528e+10 | I22: =SUM(I19:I21) -> 4.0637134e+10 | J22: =SUM(J19:J21) -> 4.1856248e+10 | ... Q22: =SUM(Q19:Q21) -> 5.1477906e+10 | R22: =IF(CONTROL!$C$12=2,SUM(R19:R21),0) -> 5.3022243e+10 | S22: =IF(CONTROL!$C$12=2,SUM(S19:S21),0) -> 5.461291e+10 | T22: =IF(CONTROL!$C$12=2,SUM(T19:T21),0) -> 5.6251297e+10 | U22: =IF(CONTROL!$C$12=2,SUM(U19:U21),0) -> 5.7938836e+10 | V22: =IF(CONTROL!$C$12=2,SUM(V19:V21),0) -> 5.9677001e+10 | W22: =SUM(W19:W21) -> 9.0377994e+11
B24: OPEX (con IVA)
B25: Conservación y Mantenimiento | C25: =+C80 -> 2124213660 | D25: =+D80 -> 2124213660 | E25: =+E80 -> 3540356100 | F25: =+F80 -> 7080712200 | G25: =+G80 -> 7080712200 | H25: =+H80 -> 7080712200 | I25: =+I80 -> 7080712200 | J25: =+J80 -> 7080712200 | ... V25: =+V80 -> 7080712200 | W25: =+SUM(C25:V25) -> 128160890820
B26: Atención al Usuario | C26: =+C81 -> 524497200 | D26: =+D81 -> 524497200 | E26: =+E81 -> 524497200 | F26: =+F81 -> 524497200 | G26: =+G81 -> 524497200 | H26: =+H81 -> 524497200 | I26: =+I81 -> 524497200 | J26: =+J81 -> 524497200 | ... V26: =+V81 -> 524497200 | W26: =+SUM(C26:V26) -> 10489944000
B27: Administración | C27: =+C82 -> 1346800000 | D27: =+D82 -> 1346800000 | E27: =+E82 -> 1346800000 | F27: =+F82 -> 1346800000 | G27: =+G82 -> 1346800000 | H27: =+H82 -> 1346800000 | I27: =+I82 -> 1346800000 | J27: =+J82 -> 1346800000 | ... V27: =+V82 -> 1346800000 | W27: =+SUM(C27:V27) -> 26936000000
B28: Explotación | C28: =+C83 -> 1598400000 | D28: =+D83 -> 1598400000 | E28: =+E83 -> 1598400000 | F28: =+F83 -> 1598400000 | G28: =+G83 -> 1598400000 | H28: =+H83 -> 1598400000 | I28: =+I83 -> 1598400000 | J28: =+J83 -> 1598400000 | ... V28: =+V83 -> 1598400000 | W28: =+SUM(C28:V28) -> 31968000000
B29: Amortización de la deuda | C29: =+C84 -> 0 | D29: =+D84 -> 5.7933473e+09 | E29: =+E84 -> 5.5600021e+09 | F29: =+F84 -> 5.5600021e+09 | G29: =+G84 -> 5.5600021e+09 | H29: =+H84 -> 5.5600021e+09 | I29: =+I84 -> 5.5600021e+09 | J29: =+J84 | ... V29: =+V84 | W29: =+SUM(C29:V29) -> 3.3593358e+10
B30: Impuestos | C30: =+SUM(C85:C90) -> 7.4284769e+08 | D30: =+SUM(D85:D90) -> 6.049838e+09 | E30: =+SUM(E85:E90) -> 1.0179366e+10 | F30: =+SUM(F85:F90) -> 7.471733e+09 | G30: =+SUM(G85:G90) -> 9.2393114e+09 | H30: =+SUM(H85:H90) -> 8.2619949e+09 | I30: =+SUM(I85:I90) -> 7.5842145e+09 | J30: =+SUM(J85:J90) -> 7.9348717e+09 | ... V30: =+SUM(V85:V90) -> 1.7054604e+10 | W30: =+SUM(C30:V30) -> 2.338578e+11
B31: TOTAL OPEX | C31: =SUM(C25:C30) -> 6.3367586e+09 | D31: =SUM(D25:D30) -> 1.7437096e+10 | E31: =SUM(E25:E30) -> 2.2749421e+10 | F31: =SUM(F25:F30) -> 2.3582144e+10 | G31: =SUM(G25:G30) -> 2.5349723e+10 | H31: =SUM(H25:H30) -> 2.4372406e+10 | I31: =SUM(I25:I30) -> 2.3694626e+10 | J31: =SUM(J25:J30) -> 1.8485281e+10 | ... Q31: =SUM(Q25:Q30) -> 2.5965303e+10 | R31: =IF(CONTROL!$C$12=2,SUM(R25:R30),0) -> 2.6716971e+10 | S31: =IF(CONTROL!$C$12=2,SUM(S25:S30),0) -> 2.7399593e+10 | T31: =IF(CONTROL!$C$12=2,SUM(T25:T30),0) -> 2.7952778e+10 | U31: =IF(CONTROL!$C$12=2,SUM(U25:U30),0) -> 2.8224562e+10 | V31: =IF(CONTROL!$C$12=2,SUM(V25:V30),0) -> 2.7605014e+10 | W31: =+SUM(C31:V31) -> 4.6500599e+11
B33: RESULTADO OPERATIVO | C33: =C22-C31-C41 -> 1.6897761e+10 | D33: =D22-D31-D41 -> 1.7516853e+10 | E33: =E22-E31-E41 -> 1.3256146e+10 | F33: =F22-F31-F41 -> 1.350659e+10 | G33: =G22-G31-G41 -> 1.2854673e+10 | H33: =H22-H31-H41 -> 1.4981122e+10 | I33: =I22-I31-I41 -> 1.6842508e+10 | J33: =J22-J31-J41 -> 2.3270967e+10 | ... V33: =V22-V31-V41 -> 3.1971988e+10 | W33: =+SUM(C33:V33) -> 4.3677395e+11
B35: CAPEX
B36: Obras de Puesta en Valor | C36: =+C94 -> 19772430000 | D36: =+D94 -> 0 | E36: =+E94 -> 0 | F36: =+F94 -> 0 | G36: =+G94 -> 0 | H36: =+H94 -> 0 | I36: =+I94 -> 0 | J36: =+J94 -> 0 | ... V36: =+V94 -> 0 | W36: =+SUM(C36:V36) -> 19772430000
B37: Obras Obligatorias | C37: =+C95 -> 0 | D37: =+D95 -> 0 | E37: =+E95 -> 9990000000 | F37: =+F95 -> 16650000000 | G37: =+G95 -> 7400000000 | H37: =+H95 -> 11840000000 | I37: =+I95 -> 17760000000 | J37: =+J95 -> 17760000000 | ... V37: =+V95 -> 0 | W37: =+SUM(C37:V37) -> 93240000000
B38: Gastos Repavimentación | C38: =+C96 -> 0 | D38: =+D96 -> 6.3333037e+09 | E38: =+E96 -> 6.3333037e+09 | F38: =+F96 -> 6.3333037e+09 | G38: =+G96 -> 6.3333037e+09 | H38: =+H96 -> 6.3333037e+09 | I38: =+I96 -> 6.3333037e+09 | J38: =+J96 -> 6.3333037e+09 | ... V38: =+V96 -> 6.3333037e+09 | W38: =+SUM(C38:V38) -> 1.2033277e+11
B39: TOTAL CAPEX | C39: =SUM(C36:C38) -> 19772430000 | D39: =SUM(D36:D38) -> 6.3333037e+09 | E39: =SUM(E36:E38) -> 16323303690 | F39: =SUM(F36:F38) -> 22983303690 | G39: =SUM(G36:G38) -> 13733303690 | H39: =SUM(H36:H38) -> 18173303690 | I39: =SUM(I36:I38) -> 24093303690 | J39: =SUM(J36:J38) -> 24093303690 | ... Q39: =SUM(Q36:Q38) -> 6.3333037e+09 | R39: =IF(CONTROL!$C$12=2,SUM(R36:R38),0) -> 6.3333037e+09 | S39: =IF(CONTROL!$C$12=2,SUM(S36:S38),0) -> 6.3333037e+09 | T39: =IF(CONTROL!$C$12=2,SUM(T36:T38),0) -> 6.3333037e+09 | U39: =IF(CONTROL!$C$12=2,SUM(U36:U38),0) -> 6.3333037e+09 | V39: =IF(CONTROL!$C$12=2,SUM(V36:V38),0) -> 6.3333037e+09 | W39: =+SUM(C39:V39) -> 233345200110
B41: GARANTÍAS | C41: =+C99 -> 100000000 | D41: =+D99 -> 100000000 | E41: =+E99 -> 100000000 | F41: =+F99 -> 100000000 | G41: =+G99 -> 100000000 | H41: =+H99 -> 100000000 | I41: =+I99 -> 100000000 | J41: =+J99 -> 100000000 | ... V41: =+V99 -> 100000000 | W41: =+SUM(C41:V41) -> 2000000000
B43: Total Egresos (con IVA) | C43: =+C31+C39+C41 -> 2.6209189e+10 | D43: =+D31+D39+D41 -> 2.38704e+10 | E43: =+E31+E39+E41 -> 3.9172725e+10 | F43: =+F31+F39+F41 -> 4.6665448e+10 | G43: =+G31+G39+G41 -> 3.9183027e+10 | H43: =+H31+H39+H41 -> 4.264571e+10 | I43: =+I31+I39+I41 -> 4.788793e+10 | J43: =+J31+J39+J41 -> 4.2678585e+10 | ... W43: =+W31+W39+W41 -> 7.0035119e+11
B45: FLUJO NETO (INGRESOS - EGRESOS) (I-E) | C45: =+C33-C39 -> -2.8746685e+09 | D45: =+D33-D39 -> 1.1183549e+10 | E45: =+E33-E39 -> -3.0671579e+09 | F45: =+F33-F39 -> -9.4767139e+09 | G45: =+G33-G39 -> -8.7863024e+08 | H45: =+H33-H39 -> -3.1921819e+09 | I45: =+I33-I39 -> -7.2507956e+09 | J45: =+J33-J39 -> -8.2233672e+08 | ... V45: =+V33-V39 -> 2.5638684e+10 | W45: =+SUM(C45:V45) -> 2.0342875e+11
B46: (I-E) ACUMULADO | C46: =C45 -> -2.8746685e+09 | D46: =+D45+C46 -> 8.3088805e+09 | E46: =+E45+D46 -> 5.2417226e+09 | F46: =+F45+E46 -> -4.2349913e+09 | G46: =+G45+F46 -> -5.1136216e+09 | H46: =+H45+G46 -> -8.3058035e+09 | I46: =+I45+H46 -> -1.5556599e+10 | J46: =+J45+I46 -> -1.6378936e+10 | K46: =+K45+J46 -> -1.1378799e+10 | ... Q46: =+Q45+P46 -> 9.1991896e+10 | R46: =IF(CONTROL!$C$12=2,R45+Q46,0) -> 1.1186386e+11 | S46: =IF(CONTROL!$C$12=2,S45+R46,0) -> 1.3264388e+11 | T46: =IF(CONTROL!$C$12=2,T45+S46,0) -> 1.5450909e+11 | U46: =IF(CONTROL!$C$12=2,U45+T46,0) -> 1.7779006e+11 | V46: =IF(CONTROL!$C$12=2,V45+U46,0) -> 2.0342875e+11
B49: TIR (Nominal) | C49: =IF(CONTROL!$C$12=2,IRR(C45:V45),IRR(C45:Q45)) -> 2.2128475
B51: VAN | C51: =+NPV(B52,C45:V45) -> 4.4958838e+10
B52: =+CONTROL!G21 -> 0.1
B54: RETORNO (VAN FLUJO NETO / VAN EGRESOS) | C54: =+C51/(NPV(B52,C43:V43)) -> 0.14937691
B58: Relación VAI/VAE | C58: =+NPV(B52,C22:V22)/NPV(B52,C43:V43) -> 1.1493769
B60: PAYBACK (año desde el que el flujo acumulado queda positivo) | C60: {=IFERROR(IF(LOOKUP(2,1/(C46:V46<0),C8:V8)>=$C$118,"No recupera",LOOKUP(2,1/(C46:V46<0),C8:V8)+1),1)} -> 10
B63: F L U J O D E F O N D O S P R O Y E C T O
B67: Tránsitos Crecimiento Anual | D67: =+D16 -> 0.03 | E67: =+E16 -> 0.03 | F67: =+F16 -> 0.03 | G67: =+G16 -> 0.03 | H67: =+H16 -> 0.03 | I67: =+I16 -> 0.03 | J67: =+J16 -> 0.03 | K67: =+K16 -> 0.03 | ... V67: =+V16 -> 0.03 | W67: TOTAL
C68: PERIODO DE CONCESIÓN
C69: 2027 | D69: 2028 | E69: 2029 | F69: 2030 | G69: 2031 | H69: 2032 | I69: 2033 | J69: 2034 | K69: 2035 | L69: 2036 | M69: 2037 | N69: 2038 | O69: 2039 | P69: 2040 | Q69: 2041 | R69: 2042 | S69: 2043 | T69: 2044 | U69: 2045 | V69: 2046
C70: 1 | D70: =+C70+1 -> 2 | E70: =+D70+1 -> 3 | F70: =+E70+1 -> 4 | G70: =+F70+1 -> 5 | H70: =+G70+1 -> 6 | I70: =+H70+1 -> 7 | J70: =+I70+1 -> 8 | K70: =+J70+1 -> 9 | ... V70: =+U70+1 -> 20
B71: INGRESOS (con IVA)
B72: Ingresos Peajes | D72: =SUM(D73:D76) -> 35053948800 | E72: =SUM(E73:E76) -> 36105567264 | F72: =SUM(F73:F76) -> 3.7188734e+10 | G72: =SUM(G73:G76) -> 3.8304396e+10 | H72: =SUM(H73:H76) -> 3.9453528e+10 | I72: =SUM(I73:I76) -> 4.0637134e+10 | J72: =SUM(J73:J76) -> 4.1856248e+10 | K72: =SUM(K73:K76) -> 4.3111936e+10 | ... V72: =SUM(V73:V76) -> 5.9677001e+10 | W72: =+SUM(C72:V72) -> 8.8044542e+11
B73: Peajes | D73: =+C114*$C$112*CONTROL!C37*(1+D67)*HIPOTESIS!D18 -> 34706880000 | E73: =C114*$C$112*CONTROL!C38*(1+D67)*(1+E67)*HIPOTESIS!E18 -> 35748086400 | F73: =C114*$C$112*CONTROL!C39*(1+D67)*(1+E67)*(1+F67)*HIPOTESIS!F18 -> 36820528992 | G73: =C114*$C$112*CONTROL!$C$40*(1+D67)*(1+E67)*(1+F67)*(1+G67)*HIPOTESIS!G18 -> 3.7925145e+10 | H73: =G73*(1+H67)*HIPOTESIS!H18 -> 3.9062899e+10 | I73: =H73*(1+I67)*HIPOTESIS!I18 -> 4.0234786e+10 | J73: =I73*(1+J67)*HIPOTESIS!J18 -> 4.144183e+10 | K73: =J73*(1+K67)*HIPOTESIS!K18 -> 4.2685085e+10 | L73: =K73*(1+L67)*HIPOTESIS!L18 -> 4.3965637e+10 | M73: =L73*(1+M67)*HIPOTESIS!M18 -> 4.5284606e+10 | N73: =M73*(1+N67)*HIPOTESIS!N18 -> 4.6643145e+10 | O73: =N73*(1+O67)*HIPOTESIS!O18 -> 4.8042439e+10 | ... V73: =U73*(1+V67)*HIPOTESIS!V18 -> 5.908614e+10 | W73: =+SUM(C73:V73) -> 8.7172814e+11
B74: Peajes adicionales | D74: =$C$115*$C$112*(1+D67)*HIPOTESIS!D19 -> 0 | E74: =+D74*(1+E67)*HIPOTESIS!E19 -> 0 | F74: =+E74*(1+F67)*HIPOTESIS!F19 -> 0 | G74: =+F74*(1+G67)*HIPOTESIS!G19 -> 0 | H74: =+G74*(1+H67)*HIPOTESIS!H19 -> 0 | I74: =+H74*(1+I67)*HIPOTESIS!I19 -> 0 | J74: =+I74*(1+J67)*HIPOTESIS!J19 -> 0 | K74: =+J74*(1+K67)*HIPOTESIS!K19 -> 0 | L74: =+K74*(1+L67)*HIPOTESIS!L19 -> 0 | ... V74: =+U74*(1+V67)*HIPOTESIS!V19 -> 0 | W74: =+SUM(C74:V74) -> 0
B75: Otros Ingresos | D75: =+(D73+D74)*0.01*HIPOTESIS!D20 -> 347068800 | E75: =+(E73+E74)*0.01*HIPOTESIS!E20 -> 357480864 | F75: =+(F73+F74)*0.01*HIPOTESIS!F20 -> 3.6820529e+08 | G75: =+(G73+G74)*0.01*HIPOTESIS!G20 -> 3.7925145e+08 | H75: =+(H73+H74)*0.01*HIPOTESIS!H20 -> 3.9062899e+08 | I75: =+(I73+I74)*0.01*HIPOTESIS!I20 -> 4.0234786e+08 | J75: =+(J73+J74)*0.01*HIPOTESIS!J20 -> 4.144183e+08 | K75: =+(K73+K74)*0.01*HIPOTESIS!K20 -> 4.2685085e+08 | ... V75: =+(V73+V74)*0.01*HIPOTESIS!V20 -> 5.908614e+08 | W75: =+SUM(C75:V75) -> 8.7172814e+09
B76: Ingresos Crédito LP | C76: =+C116 -> 23334520011 | W76: =+SUM(C76:V76) -> 23334520011
B77: Total Ingresos | C77: =SUM(C73:C76) -> 23334520011 | D77: =SUM(D73:D76) -> 35053948800 | E77: =SUM(E73:E76) -> 36105567264 | F77: =SUM(F73:F76) -> 3.7188734e+10 | G77: =SUM(G73:G76) -> 3.8304396e+10 | H77: =SUM(H73:H76) -> 3.9453528e+10 | I77: =SUM(I73:I76) -> 4.0637134e+10 | J77: =SUM(J73:J76) -> 4.1856248e+10 | ... Q77: =SUM(Q73:Q76) -> 5.1477906e+10 | R77: =IF(CONTROL!$C$12=2,SUM(R73:R76),0) -> 5.3022243e+10 | S77: =IF(CONTROL!$C$12=2,SUM(S73:S76),0) -> 5.461291e+10 | T77: =IF(CONTROL!$C$12=2,SUM(T73:T76),0) -> 5.6251297e+10 | U77: =IF(CONTROL!$C$12=2,SUM(U73:U76),0) -> 5.7938836e+10 | V77: =IF(CONTROL!$C$12=2,SUM(V73:V76),0) -> 5.9677001e+10 | W77: =SUM(W73:W76) -> 9.0377994e+11
B79: OPEX (con IVA)
B80: Conservación y Mantenimiento | C80: =+OPEX!E19*HIPOTESIS!C24 -> 2124213660 | D80: =+OPEX!F19*HIPOTESIS!D24 -> 2124213660 | E80: =+OPEX!G19*HIPOTESIS!E24 -> 3540356100 | F80: =+OPEX!H19*HIPOTESIS!F24 -> 7080712200 | G80: =+OPEX!I19*HIPOTESIS!G24 -> 7080712200 | H80: =+OPEX!J19*HIPOTESIS!H24 -> 7080712200 | I80: =+OPEX!K19*HIPOTESIS!I24 -> 7080712200 | J80: =+OPEX!L19*HIPOTESIS!J24 -> 7080712200 | ... V80: =+OPEX!X19*HIPOTESIS!V24 -> 7080712200 | W80: =+SUM(C80:V80) -> 128160890820
B81: Atención al Usuario | C81: =+OPEX!E20*HIPOTESIS!C25 -> 524497200 | D81: =+OPEX!F20*HIPOTESIS!D25 -> 524497200 | E81: =+OPEX!G20*HIPOTESIS!E25 -> 524497200 | F81: =+OPEX!H20*HIPOTESIS!F25 -> 524497200 | G81: =+OPEX!I20*HIPOTESIS!G25 -> 524497200 | H81: =+OPEX!J20*HIPOTESIS!H25 -> 524497200 | I81: =+OPEX!K20*HIPOTESIS!I25 -> 524497200 | J81: =+OPEX!L20*HIPOTESIS!J25 -> 524497200 | ... V81: =+OPEX!X20*HIPOTESIS!V25 -> 524497200 | W81: =+SUM(C81:V81) -> 10489944000
B82: Administración | C82: =+OPEX!E21*HIPOTESIS!C26 -> 1346800000 | D82: =+OPEX!F21*HIPOTESIS!D26 -> 1346800000 | E82: =+OPEX!G21*HIPOTESIS!E26 -> 1346800000 | F82: =+OPEX!H21*HIPOTESIS!F26 -> 1346800000 | G82: =+OPEX!I21*HIPOTESIS!G26 -> 1346800000 | H82: =+OPEX!J21*HIPOTESIS!H26 -> 1346800000 | I82: =+OPEX!K21*HIPOTESIS!I26 -> 1346800000 | J82: =+OPEX!L21*HIPOTESIS!J26 -> 1346800000 | ... V82: =+OPEX!X21*HIPOTESIS!V26 -> 1346800000 | W82: =+SUM(C82:V82) -> 26936000000
B83: Explotación | C83: =+OPEX!E22*HIPOTESIS!C27 -> 1598400000 | D83: =+OPEX!F22*HIPOTESIS!D27 -> 1598400000 | E83: =+OPEX!G22*HIPOTESIS!E27 -> 1598400000 | F83: =+OPEX!H22*HIPOTESIS!F27 -> 1598400000 | G83: =+OPEX!I22*HIPOTESIS!G27 -> 1598400000 | H83: =+OPEX!J22*HIPOTESIS!H27 -> 1598400000 | I83: =+OPEX!K22*HIPOTESIS!I27 -> 1598400000 | J83: =+OPEX!L22*HIPOTESIS!J27 -> 1598400000 | ... V83: =+OPEX!X22*HIPOTESIS!V27 -> 1598400000 | W83: =+SUM(C83:V83) -> 31968000000
B84: Amortización de la deuda | C84: =IF(CONTROL!$G$32="NO",+'PRESTAMO '!$D$13+'PRESTAMO '!$D$9,0) -> 0 | D84: =IF(CONTROL!G32="NO",'PRESTAMO '!$D14,'PRESTAMO '!D13+'PRESTAMO '!D9) -> 5.7933473e+09 | E84: =IF(CONTROL!$G$32="NO",'PRESTAMO '!$D15,'PRESTAMO '!$D$14) -> 5.5600021e+09 | F84: =IF(CONTROL!$G$32="NO",'PRESTAMO '!$D16,'PRESTAMO '!$D$15) -> 5.5600021e+09 | G84: =IF(CONTROL!$G$32="NO",'PRESTAMO '!$D17,'PRESTAMO '!$D$16) -> 5.5600021e+09 | H84: =IF(CONTROL!$G$32="NO",'PRESTAMO '!$D18,'PRESTAMO '!$D$17) -> 5.5600021e+09 | I84: =IF(CONTROL!$G$32="NO",'PRESTAMO '!$D19,'PRESTAMO '!$D$18) -> 5.5600021e+09 | J84: =IF(CONTROL!$G$32="NO",'PRESTAMO '!$D20,'PRESTAMO '!$D$19) | K84: =IF(CONTROL!$G$32="NO",'PRESTAMO '!$D21,'PRESTAMO '!$D$20) | L84: =IF(CONTROL!$G$32="NO",'PRESTAMO '!$D22,'PRESTAMO '!$D$21) | M84: =IF(CONTROL!$G$32="NO",'PRESTAMO '!$D23,'PRESTAMO '!$D$22) | N84: =IF(CONTROL!$G$32="NO",'PRESTAMO '!$D24,'PRESTAMO '!$D$23) | O84: =IF(CONTROL!$G$32="NO",'PRESTAMO '!$D25,'PRESTAMO '!$D$24) | P84: =IF(CONTROL!$G$32="NO",'PRESTAMO '!$D26,'PRESTAMO '!$D$25) | Q84: =IF(CONTROL!$G$32="NO",'PRESTAMO '!$D27,'PRESTAMO '!$D$26) | R84: =IF(CONTROL!$C$12=2,IF(CONTROL!$G$32="NO",'PRESTAMO '!$D28,'PRESTAMO '!$D27),0) | S84: =IF(CONTROL!$C$12=2,IF(CONTROL!$G$32="NO",'PRESTAMO '!$D29,'PRESTAMO '!$D28),0) | T84: =IF(CONTROL!$C$12=2,IF(CONTROL!$G$32="NO",'PRESTAMO '!$D30,'PRESTAMO '!$D29),0) | U84: =IF(CONTROL!$C$12=2,IF(CONTROL!$G$32="NO",'PRESTAMO '!$D31,'PRESTAMO '!$D30),0) | V84: =IF(CONTROL!$C$12=2,IF(CONTROL!$G$32="NO",'PRESTAMO '!$D32,'PRESTAMO '!$D31),0) | W84: =+SUM(C84:V84) -> 3.3593358e+10
B85: IVA Saldo a Pagar | C85: =+IMPUESTOS!D41 -> 0 | D85: =+IMPUESTOS!E41 -> 2.535362e+08 | E85: =+IMPUESTOS!F41 -> 2.5988413e+09 | F85: =+IMPUESTOS!G41 -> 1.1691756e+09 | G85: =+IMPUESTOS!H41 -> 2.9681748e+09 | H85: =+IMPUESTOS!I41 -> 2.3970324e+09 | I85: =+IMPUESTOS!J41 -> 1.5750136e+09 | J85: =+IMPUESTOS!K41 -> 1.7865953e+09 | ... V85: =+IMPUESTOS!W41 -> 7.9617674e+09 | W85: =+SUM(C85:V85) -> 8.8136841e+10
B86: Impuesto a las Ganancias | C86: =+IMPUESTOS!D26 -> 0 | D86: =+IMPUESTOS!E26 -> 4.0437148e+09 | E86: =+IMPUESTOS!F26 -> 5.7892452e+09 | F86: =+IMPUESTOS!G26 -> 4.4714244e+09 | G86: =+IMPUESTOS!H26 -> 4.3989546e+09 | H86: =+IMPUESTOS!I26 -> 4.4133335e+09 | I86: =+IMPUESTOS!J26 -> 4.514023e+09 | J86: =+IMPUESTOS!K26 -> 4.6082432e+09 | ... V86: =+IMPUESTOS!W26 -> 6.8971179e+09 | W86: =+SUM(C86:V86) -> 1.1073221e+11
B87: Impuesto a los Ingresos Brutos | C87: =+IMPUESTOS!D16 -> 0 | D87: =+IMPUESTOS!E16 -> 7.2425514e+08 | E87: =+IMPUESTOS!F16 -> 7.4598279e+08 | F87: =+IMPUESTOS!G16 -> 7.6836228e+08 | G87: =+IMPUESTOS!H16 -> 7.9141315e+08 | H87: =+IMPUESTOS!I16 -> 8.1515554e+08 | I87: =+IMPUESTOS!J16 -> 8.3961021e+08 | J87: =+IMPUESTOS!K16 -> 8.6479851e+08 | ... V87: =+IMPUESTOS!W16 -> 1.2329959e+09 | W87: =+SUM(C87:V87) -> 1.8191021e+10
B88: Impuestos Municipales | C88: =+IMPUESTOS!D22 -> 0 | D88: =+IMPUESTOS!E22 -> 1.4485103e+08 | E88: =+IMPUESTOS!F22 -> 1.4919656e+08 | F88: =+IMPUESTOS!G22 -> 1.5367246e+08 | G88: =+IMPUESTOS!H22 -> 1.5828263e+08 | H88: =+IMPUESTOS!I22 -> 1.6303111e+08 | I88: =+IMPUESTOS!J22 -> 1.6792204e+08 | J88: =+IMPUESTOS!K22 -> 1.729597e+08 | ... V88: =+IMPUESTOS!W22 -> 2.4659918e+08 | W88: =+SUM(C88:V88) -> 3.6382042e+09
B89: Impuesto de Sellos | C89: =+IMPUESTOS!D20 -> 4.6283345e+08 | D89: =+IMPUESTOS!E20 -> 4.6283345e+08 | E89: =+IMPUESTOS!F20 -> 4.6283345e+08 | F89: =+IMPUESTOS!G20 -> 4.6283345e+08 | G89: =+IMPUESTOS!H20 -> 4.6283345e+08 | H89: =+IMPUESTOS!I20 -> 0 | I89: =+IMPUESTOS!J20 -> 0 | J89: =+IMPUESTOS!K20 -> 0 | ... V89: =+IMPUESTOS!W20 -> 0 | W89: =+SUM(C89:V89) -> 2.3141673e+09
B90: Impuesto a los Débitos y Créditos | C90: =+IMPUESTOS!D24 -> 2.8001424e+08 | D90: =+IMPUESTOS!E24 -> 4.2064739e+08 | E90: =+IMPUESTOS!F24 -> 4.3326681e+08 | F90: =+IMPUESTOS!G24 -> 4.4626481e+08 | G90: =+IMPUESTOS!H24 -> 4.5965276e+08 | H90: =+IMPUESTOS!I24 -> 4.7344234e+08 | I90: =+IMPUESTOS!J24 -> 4.8764561e+08 | J90: =+IMPUESTOS!K24 -> 5.0227498e+08 | ... V90: =+IMPUESTOS!W24 -> 7.1612402e+08 | W90: =+SUM(C90:V90) -> 1.0845359e+10
B91: Subtotal Egresos | C91: =SUM(C80:C90) -> 6.3367586e+09 | D91: =SUM(D80:D90) -> 1.7437096e+10 | E91: =SUM(E80:E90) -> 2.2749421e+10 | F91: =SUM(F80:F90) -> 2.3582144e+10 | G91: =SUM(G80:G90) -> 2.5349723e+10 | H91: =SUM(H80:H90) -> 2.4372406e+10 | I91: =SUM(I80:I90) -> 2.3694626e+10 | J91: =SUM(J80:J90) -> 1.8485281e+10 | ... Q91: =SUM(Q80:Q90) -> 2.5965303e+10 | R91: =IF(CONTROL!$C$12=2,SUM(R80:R90),0) -> 2.6716971e+10 | S91: =IF(CONTROL!$C$12=2,SUM(S80:S90),0) -> 2.7399593e+10 | T91: =IF(CONTROL!$C$12=2,SUM(T80:T90),0) -> 2.7952778e+10 | U91: =IF(CONTROL!$C$12=2,SUM(U80:U90),0) -> 2.8224562e+10 | V91: =IF(CONTROL!$C$12=2,SUM(V80:V90),0) -> 2.7605014e+10 | W91: =+SUM(C91:V91) -> 4.6500599e+11
B93: Resultado Operativo | C93: =C77-C91-C99 -> 1.6897761e+10 | D93: =D77-D91-D99 -> 1.7516853e+10 | E93: =E77-E91-E99 -> 1.3256146e+10 | F93: =F77-F91-F99 -> 1.350659e+10 | G93: =G77-G91-G99 -> 1.2854673e+10 | H93: =H77-H91-H99 -> 1.4981122e+10 | I93: =I77-I91-I99 -> 1.6842508e+10 | J93: =J77-J91-J99 -> 2.3270967e+10 | ... V93: =V77-V91-V99 -> 3.1971988e+10 | W93: =+SUM(C93:V93) -> 4.3677395e+11
B94: Obras de Puesta en Valor | C94: =+CAPEX!D17*HIPOTESIS!C31 -> 19772430000 | D94: =+CAPEX!E17*HIPOTESIS!D31 -> 0 | E94: =+CAPEX!F17*HIPOTESIS!E31 -> 0 | F94: =+CAPEX!G17*HIPOTESIS!F31 -> 0 | G94: =+CAPEX!H17*HIPOTESIS!G31 -> 0 | H94: =+CAPEX!I17*HIPOTESIS!H31 -> 0 | I94: =+CAPEX!J17*HIPOTESIS!I31 -> 0 | J94: =+CAPEX!K17*HIPOTESIS!J31 -> 0 | ... V94: =+CAPEX!W17*HIPOTESIS!V31 -> 0 | W94: =+SUM(C94:V94) -> 19772430000
B95: Obras Obligatorias | C95: =+CAPEX!D18*HIPOTESIS!C32 -> 0 | D95: =+CAPEX!E18*HIPOTESIS!D32 -> 0 | E95: =+CAPEX!F18*HIPOTESIS!E32 -> 9990000000 | F95: =+CAPEX!G18*HIPOTESIS!F32 -> 16650000000 | G95: =+CAPEX!H18*HIPOTESIS!G32 -> 7400000000 | H95: =+CAPEX!I18*HIPOTESIS!H32 -> 11840000000 | I95: =+CAPEX!J18*HIPOTESIS!I32 -> 17760000000 | J95: =+CAPEX!K18*HIPOTESIS!J32 -> 17760000000 | ... V95: =+CAPEX!W18*HIPOTESIS!V32 -> 0 | W95: =+SUM(C95:V95) -> 93240000000
B96: Gastos Repavimentación | C96: =+CAPEX!D19*HIPOTESIS!C33 -> 0 | D96: =+CAPEX!E19*HIPOTESIS!D33 -> 6.3333037e+09 | E96: =+CAPEX!F19*HIPOTESIS!E33 -> 6.3333037e+09 | F96: =+CAPEX!G19*HIPOTESIS!F33 -> 6.3333037e+09 | G96: =+CAPEX!H19*HIPOTESIS!G33 -> 6.3333037e+09 | H96: =+CAPEX!I19*HIPOTESIS!H33 -> 6.3333037e+09 | I96: =+CAPEX!J19*HIPOTESIS!I33 -> 6.3333037e+09 | J96: =+CAPEX!K19*HIPOTESIS!J33 -> 6.3333037e+09 | ... V96: =+CAPEX!W19*HIPOTESIS!V33 -> 6.3333037e+09 | W96: =+SUM(C96:V96) -> 1.2033277e+11
B97: CAPEX | C97: =SUM(C94:C96) -> 19772430000 | D97: =SUM(D94:D96) -> 6.3333037e+09 | E97: =SUM(E94:E96) -> 16323303690 | F97: =SUM(F94:F96) -> 22983303690 | G97: =SUM(G94:G96) -> 13733303690 | H97: =SUM(H94:H96) -> 18173303690 | I97: =SUM(I94:I96) -> 24093303690 | J97: =SUM(J94:J96) -> 24093303690 | ... Q97: =SUM(Q94:Q96) -> 6.3333037e+09 | R97: =IF(CONTROL!$C$12=2,SUM(R94:R96),0) -> 6.3333037e+09 | S97: =IF(CONTROL!$C$12=2,SUM(S94:S96),0) -> 6.3333037e+09 | T97: =IF(CONTROL!$C$12=2,SUM(T94:T96),0) -> 6.3333037e+09 | U97: =IF(CONTROL!$C$12=2,SUM(U94:U96),0) -> 6.3333037e+09 | V97: =IF(CONTROL!$C$12=2,SUM(V94:V96),0) -> 6.3333037e+09 | W97: =+SUM(C97:V97) -> 233345200110
B99: GARANTÍAS | C99: =+CONTROL!$F$44+CONTROL!$F$55 -> 100000000 | D99: =+CONTROL!$F$44+CONTROL!$F$55 -> 100000000 | E99: =+CONTROL!$F$44+CONTROL!$F$55 -> 100000000 | F99: =+CONTROL!$F$44+CONTROL!$F$55 -> 100000000 | G99: =+CONTROL!$F$44+CONTROL!$F$55 -> 100000000 | H99: =+CONTROL!$F$45+CONTROL!$F$56 -> 100000000 | I99: =+CONTROL!$F$45+CONTROL!$F$56 -> 100000000 | J99: =+CONTROL!$F$45+CONTROL!$F$56 -> 100000000 | K99: =+CONTROL!$F$45+CONTROL!$F$56 -> 100000000 | L99: =+CONTROL!$F$45+CONTROL!$F$56 -> 100000000 | M99: =+CONTROL!$F$45+CONTROL!$F$56 -> 100000000 | N99: =+CONTROL!$F$45+CONTROL!$F$56 -> 100000000 | O99: =+CONTROL!$F$45+CONTROL!$F$56 -> 100000000 | ... V99: =+CONTROL!$F$45+CONTROL!$F$56 -> 100000000 | W99: =+SUM(C99:V99) -> 2000000000
B101: Total Egresos (con IVA) | C101: =+C91+C97+C99 -> 2.6209189e+10 | D101: =+D91+D97+D99 -> 2.38704e+10 | E101: =+E91+E97+E99 -> 3.9172725e+10 | F101: =+F91+F97+F99 -> 4.6665448e+10 | G101: =+G91+G97+G99 -> 3.9183027e+10 | H101: =+H91+H97+H99 -> 4.264571e+10 | I101: =+I91+I97+I99 -> 4.788793e+10 | J101: =+J91+J97+J99 -> 4.2678585e+10 | ... W101: =+W91+W97+W99 -> 7.0035119e+11
B103: FLUJO NETO | C103: =+C93-C97 -> -2.8746685e+09 | D103: =+D93-D97 -> 1.1183549e+10 | E103: =+E93-E97 -> -3.0671579e+09 | F103: =+F93-F97 -> -9.4767139e+09 | G103: =+G93-G97 -> -8.7863024e+08 | H103: =+H93-H97 -> -3.1921819e+09 | I103: =+I93-I97 -> -7.2507956e+09 | J103: =+J93-J97 -> -8.2233672e+08 | ... Q103: =+Q93-Q97 -> 1.9079299e+10 | R103: =IF(CONTROL!$C$12=2,R93-R97,0) -> 1.9871968e+10 | S103: =IF(CONTROL!$C$12=2,S93-S97,0) -> 2.0780014e+10 | T103: =IF(CONTROL!$C$12=2,T93-T97,0) -> 2.1865216e+10 | U103: =IF(CONTROL!$C$12=2,U93-U97,0) -> 2.328097e+10 | V103: =IF(CONTROL!$C$12=2,V93-V97,0) -> 2.5638684e+10 | W103: =+SUM(C103:V103) -> 2.0342875e+11
B104: FLUJO NETO ACUMULADO | C104: =C103 -> -2.8746685e+09 | D104: =+D103+C104 -> 8.3088805e+09 | E104: =+E103+D104 -> 5.2417226e+09 | F104: =+F103+E104 -> -4.2349913e+09 | G104: =+G103+F104 -> -5.1136216e+09 | H104: =+H103+G104 -> -8.3058035e+09 | I104: =+I103+H104 -> -1.5556599e+10 | J104: =+J103+I104 -> -1.6378936e+10 | K104: =+K103+J104 -> -1.1378799e+10 | ... Q104: =+Q103+P104 -> 9.1991896e+10 | R104: =IF(CONTROL!$C$12=2,R103+Q104,0) -> 1.1186386e+11 | S104: =IF(CONTROL!$C$12=2,S103+R104,0) -> 1.3264388e+11 | T104: =IF(CONTROL!$C$12=2,T103+S104,0) -> 1.5450909e+11 | U104: =IF(CONTROL!$C$12=2,U103+T104,0) -> 1.7779006e+11 | V104: =IF(CONTROL!$C$12=2,V103+U104,0) -> 2.0342875e+11
B107: TIR (Nominal) (con IVA) | C107: =IF(CONTROL!$C$12=2,IRR($C$103:$V$103),IRR($C$103:$Q$103)) -> 2.2128475
B108: VAN | C108: =IF(CONTROL!$C$12=2,NPV(B109,$C$103:$V$103),NPV(B109,$C$103:$Q$103)) -> 4.4958838e+10
B109: =+CONTROL!G21 -> 0.1
B110: VAN/VAE | C110: =IF(CONTROL!$C$12=2,C108/(NPV(B109,C101:V101)),C108/(NPV(B109,C101:Q101))) -> 0.14937691
B111: PAYOUT en Años (flujo acumulado positivo definitivo) | C111: {=IFERROR(IF(LOOKUP(2,1/(C104:V104<0),C8:V8)>=$C$118,"No recupera",LOOKUP(2,1/(C104:V104<0),C8:V8)+1),1)} -> 10
B112: Tarifa | C112: =+CONTROL!C24 -> 4680
B113: Sin uso | C113: =+CONTROL!C19 -> 0
B114: UTEQUIS | C114: =+CONTROL!C20 -> 7200000
B115: UTEQUIS peajes adicionales | C115: =+CONTROL!C21 -> 0
B116: Monto del Crédito | C116: =+CONTROL!G24 -> 23334520011
B117: TASA (TNA) | C117: =CONTROL!G26 -> 0.085
B118: PLAZO (AÑOS) | C118: =+IF(CONTROL!$C$12=2,20,15) -> 20

Sheet CAPEX
B2: =+FLUJO!B4 -> 1 de junio 2026 | D2: =+FLUJO!C4 -> 2027 | E2: =+FLUJO!D4 -> 2028 | F2: =+FLUJO!E4 -> 2029 | G2: =+FLUJO!F4 -> 2030 | H2: =+FLUJO!G4 -> 2031 | I2: =+FLUJO!H4 -> 2032 | J2: =+FLUJO!I4 -> 2033 | K2: =+FLUJO!J4 -> 2034 | ... W2: =+FLUJO!V4 -> 2046
B3: =+CONTROL!B2 -> TIR Nominal (con IVA) | D3: =+FLUJO!C5 -> 46388 | E3: =+FLUJO!D5 -> 46753 | F3: =+FLUJO!E5 -> 47119 | G3: =+FLUJO!F5 -> 47484 | H3: =+FLUJO!G5 -> 47849 | I3: =+FLUJO!H5 -> 48214 | J3: =+FLUJO!I5 -> 48580 | K3: =+FLUJO!J5 -> 48945 | ... W3: =+FLUJO!V5 -> 53328
B4: =+FLUJO!B6 -> 2.2128475 | D4: =+FLUJO!C6 -> 46752 | E4: =+FLUJO!D6 -> 47118 | F4: =+FLUJO!E6 -> 47483 | G4: =+FLUJO!F6 -> 47848 | H4: =+FLUJO!G6 -> 48213 | I4: =+FLUJO!H6 -> 48579 | J4: =+FLUJO!I6 -> 48944 | K4: =+FLUJO!J6 -> 49309 | ... W4: =+FLUJO!V6 -> 53692
B6: Año de Concesión | D6: 1 | E6: 2 | F6: 3 | G6: 4 | H6: 5 | I6: 6 | J6: 7 | K6: 8 | L6: 9 | M6: 10 | N6: 11 | O6: 12 | P6: 13 | Q6: 14 | R6: 15 | S6: 16 | T6: 17 | U6: 18 | V6: 19 | W6: 20
B7: Días del Año | D7: =+D4-D3+1 -> 365 | E7: =+E4-E3+1 -> 366 | F7: =+F4-F3+1 -> 365 | G7: =+G4-G3+1 -> 365 | H7: =+H4-H3+1 -> 365 | I7: =+I4-I3+1 -> 366 | J7: =+J4-J3+1 -> 365 | K7: =+K4-K3+1 -> 365 | ... W7: =+W4-W3+1 -> 365
B8: Días del Año (Operación) | D8: =+-D3+D4+1 -> 365 | E8: =+E7 -> 366 | F8: =+F7 -> 365 | G8: =+G7 -> 365 | H8: =+H7 -> 365 | I8: =+I7 -> 366 | J8: =+J7 -> 365 | K8: =+K7 -> 365 | L8: =+L7 -> 365 | ... W8: =+W7 -> 365
B9: Días del Año (Construcción) | D9: =+D8 -> 365 | E9: =+E8 -> 366 | F9: =+F8 -> 365 | G9: =+G8 -> 365 | H9: =+H8 -> 365 | I9: =+I8 -> 366 | J9: =+J8 -> 365 | K9: =+K8 -> 365 | ... W9: =+W8 -> 365
B10: Factor de Ingresos | D10: =+HIPOTESIS!C11 -> 1 | E10: =+HIPOTESIS!D11 -> 1 | F10: =+HIPOTESIS!E11 -> 1 | G10: =+HIPOTESIS!F11 -> 1 | H10: =+HIPOTESIS!G11 -> 1 | I10: =+HIPOTESIS!H11 -> 1 | J10: =+HIPOTESIS!I11 -> 1 | K10: =+HIPOTESIS!J11 -> 1 | ... W10: =+HIPOTESIS!V11 -> 1
B11: Factor de Operación | D11: =+HIPOTESIS!C12 -> 1 | E11: =+HIPOTESIS!D12 -> 1 | F11: =+HIPOTESIS!E12 -> 1 | G11: =+HIPOTESIS!F12 -> 1 | H11: =+HIPOTESIS!G12 -> 1 | I11: =+HIPOTESIS!H12 -> 1 | J11: =+HIPOTESIS!I12 -> 1 | K11: =+HIPOTESIS!J12 -> 1 | ... W11: =+HIPOTESIS!V12 -> 1
B12: Factor de Construcción | D12: =+HIPOTESIS!C13 -> 1 | E12: =+HIPOTESIS!D13 -> 1 | F12: =+HIPOTESIS!E13 -> 1 | G12: =+HIPOTESIS!F13 -> 1 | H12: =+HIPOTESIS!G13 -> 1 | I12: =+HIPOTESIS!H13 -> 1 | J12: =+HIPOTESIS!I13 -> 1 | K12: =+HIPOTESIS!J13 -> 1 | ... W12: =+HIPOTESIS!V13 -> 1
B14: Sensibilidad Obras Obligatorias | C14: =+CONTROL!C29 -> 0 | D14: =+C14 -> 0 | E14: =+D14 -> 0 | F14: =+E14 -> 0 | G14: =+F14 -> 0 | H14: =+G14 -> 0 | I14: =+H14 -> 0 | J14: =+I14 -> 0 | K14: =+J14 -> 0 | ... W14: =+V14 -> 0
B15: Sensibilidad Gastos de Repavimentación | C15: =+CONTROL!C30 -> 0 | D15: =+C15 -> 0 | E15: =+D15 -> 0 | F15: =+E15 -> 0 | G15: =+F15 -> 0 | H15: =+G15 -> 0 | I15: =+H15 -> 0 | J15: =+I15 -> 0 | K15: =+J15 -> 0 | ... W15: =+V15 -> 0
X16: TOTAL
B17: Obras de Puesta en Valor + Obrador + Construcción Puestos | D17: =+INPUTS!B7*(1+D14) -> 19772430000 | X17: =+SUM(D17:W17) -> 19772430000
B18: Repavimentación Inicial + Obras Obligatorias | E18: =+INPUTS!C7*(1+E14) -> 0 | F18: =+INPUTS!D7*(1+F14) -> 9990000000 | G18: =+INPUTS!E7*(1+G14) -> 16650000000 | H18: =+INPUTS!F7*(1+H14) -> 7400000000 | I18: =+INPUTS!G7*(1+I14) -> 11840000000 | J18: =+INPUTS!H7*(1+J14) -> 17760000000 | K18: =+INPUTS!I7*(1+K14) -> 17760000000 | L18: =+INPUTS!J7*(1+L14) -> 11840000000 | ... W18: =+INPUTS!U7*(1+W14) -> 0 | X18: =+SUM(D18:W18) -> 93240000000
B19: Gastos Repavimentación | D19: =+INPUTS!B11*(1+D15) -> 0 | E19: =+INPUTS!C11*(1+E15) -> 6.3333037e+09 | F19: =+INPUTS!D11*(1+F15) -> 6.3333037e+09 | G19: =+INPUTS!E11*(1+G15) -> 6.3333037e+09 | H19: =+INPUTS!F11*(1+H15) -> 6.3333037e+09 | I19: =+INPUTS!G11*(1+I15) -> 6.3333037e+09 | J19: =+INPUTS!H11*(1+J15) -> 6.3333037e+09 | K19: =+INPUTS!I11*(1+K15) -> 6.3333037e+09 | ... W19: =+INPUTS!U11*(1+W15) -> 6.3333037e+09 | X19: =+SUM(D19:W19) -> 1.2033277e+11
B20: CAPEX TOTAL | D20: =SUM(D17:D19) -> 19772430000 | E20: =SUM(E17:E19) -> 6.3333037e+09 | F20: =SUM(F17:F19) -> 16323303690 | G20: =SUM(G17:G19) -> 22983303690 | H20: =SUM(H17:H19) -> 13733303690 | I20: =SUM(I17:I19) -> 18173303690 | J20: =SUM(J17:J19) -> 24093303690 | K20: =SUM(K17:K19) -> 24093303690 | ... R20: =SUM(R17:R19) -> 6.3333037e+09 | S20: =IF(CONTROL!$C$12=2,SUM(S17:S19),0) -> 6.3333037e+09 | T20: =IF(CONTROL!$C$12=2,SUM(T17:T19),0) -> 6.3333037e+09 | U20: =IF(CONTROL!$C$12=2,SUM(U17:U19),0) -> 6.3333037e+09 | V20: =IF(CONTROL!$C$12=2,SUM(V17:V19),0) -> 6.3333037e+09 | W20: =IF(CONTROL!$C$12=2,SUM(W17:W19),0) -> 6.3333037e+09 | X20: =+SUM(D20:W20) -> 233345200110

Sheet AMORTIZACIONES
B3: AMORTIZACION en 5 Años (vida útil en CONTROL) tanto las Obras como para las Repavimentaciones
B5: CONCEPTO | D5: Año 1 | E5: Año 2 | F5: Año 3 | G5: Año 4 | H5: Año 5 | I5: Año 6 | J5: Año 7 | K5: Año 8 | L5: Año 9 | M5: Año 10 | N5: Año 11 | O5: Año 12 | P5: Año 13 | Q5: Año 14 | R5: Año 15 | S5: Año 16 | T5: Año 17 | U5: Año 18 | V5: Año 19 | W5: Año 20 | X5: TOTAL
B6: Año de concesión (n°) | D6: 1 | E6: 2 | F6: 3 | G6: 4 | H6: 5 | I6: 6 | J6: 7 | K6: 8 | L6: 9 | M6: 10 | N6: 11 | O6: 12 | P6: 13 | Q6: 14 | R6: 15 | S6: 16 | T6: 17 | U6: 18 | V6: 19 | W6: 20
B7: INVERSIONES (SIN IVA) | D7: =+(SUM(FLUJO!C94:C95)*IMPUESTOS!$AA$29)/(1+IMPUESTOS!$AA$21)*(D$6<=FLUJO!$C$118) -> 1.6340851e+10 | E7: =+(SUM(FLUJO!D94:D95)*IMPUESTOS!$AA$29)/(1+IMPUESTOS!$AA$21)*(E$6<=FLUJO!$C$118) -> 0 | F7: =+(SUM(FLUJO!E94:E95)*IMPUESTOS!$AA$29)/(1+IMPUESTOS!$AA$21)*(F$6<=FLUJO!$C$118) -> 8.2561983e+09 | G7: =+(SUM(FLUJO!F94:F95)*IMPUESTOS!$AA$29)/(1+IMPUESTOS!$AA$21)*(G$6<=FLUJO!$C$118) -> 1.3760331e+10 | H7: =+(SUM(FLUJO!G94:G95)*IMPUESTOS!$AA$29)/(1+IMPUESTOS!$AA$21)*(H$6<=FLUJO!$C$118) -> 6.1157025e+09 | I7: =+(SUM(FLUJO!H94:H95)*IMPUESTOS!$AA$29)/(1+IMPUESTOS!$AA$21)*(I$6<=FLUJO!$C$118) -> 9.785124e+09 | J7: =+(SUM(FLUJO!I94:I95)*IMPUESTOS!$AA$29)/(1+IMPUESTOS!$AA$21)*(J$6<=FLUJO!$C$118) -> 1.4677686e+10 | K7: =+(SUM(FLUJO!J94:J95)*IMPUESTOS!$AA$29)/(1+IMPUESTOS!$AA$21)*(K$6<=FLUJO!$C$118) -> 1.4677686e+10 | ... W7: =+(SUM(FLUJO!V94:V95)*IMPUESTOS!$AA$29)/(1+IMPUESTOS!$AA$21)*(W$6<=FLUJO!$C$118) -> 0 | X7: =SUM(D7:W7) -> 9.3398702e+10
B9: PERIODOS | D9: =MAX(1,MIN(CONTROL!$C$58,FLUJO!$C$118-D$6+1)) -> 5 | E9: =MAX(1,MIN(CONTROL!$C$58,FLUJO!$C$118-E$6+1)) -> 5 | F9: =MAX(1,MIN(CONTROL!$C$58,FLUJO!$C$118-F$6+1)) -> 5 | G9: =MAX(1,MIN(CONTROL!$C$58,FLUJO!$C$118-G$6+1)) -> 5 | H9: =MAX(1,MIN(CONTROL!$C$58,FLUJO!$C$118-H$6+1)) -> 5 | I9: =MAX(1,MIN(CONTROL!$C$58,FLUJO!$C$118-I$6+1)) -> 5 | J9: =MAX(1,MIN(CONTROL!$C$58,FLUJO!$C$118-J$6+1)) -> 5 | K9: =MAX(1,MIN(CONTROL!$C$58,FLUJO!$C$118-K$6+1)) -> 5 | ... W9: =MAX(1,MIN(CONTROL!$C$58,FLUJO!$C$118-W$6+1)) -> 1
B11: Cálculo integrado en la fila TOTAL (cada inversión se amortiza en sus períodos, sin pasar el fin de la concesión)
B18: TOTAL AMORTIZACIÓN OBRAS | D18: =SUMPRODUCT($D$7:$W$7/$D$9:$W$9*($D$6:$W$6<=D$6)*(D$6-$D$6:$W$6<$D$9:$W$9)) -> 3.2681702e+09 | E18: =SUMPRODUCT($D$7:$W$7/$D$9:$W$9*($D$6:$W$6<=E$6)*(E$6-$D$6:$W$6<$D$9:$W$9)) -> 3.2681702e+09 | F18: =SUMPRODUCT($D$7:$W$7/$D$9:$W$9*($D$6:$W$6<=F$6)*(F$6-$D$6:$W$6<$D$9:$W$9)) -> 4.9194099e+09 | G18: =SUMPRODUCT($D$7:$W$7/$D$9:$W$9*($D$6:$W$6<=G$6)*(G$6-$D$6:$W$6<$D$9:$W$9)) -> 7.671476e+09 | H18: =SUMPRODUCT($D$7:$W$7/$D$9:$W$9*($D$6:$W$6<=H$6)*(H$6-$D$6:$W$6<$D$9:$W$9)) -> 8.8946165e+09 | I18: =SUMPRODUCT($D$7:$W$7/$D$9:$W$9*($D$6:$W$6<=I$6)*(I$6-$D$6:$W$6<$D$9:$W$9)) -> 7.5834711e+09 | J18: =SUMPRODUCT($D$7:$W$7/$D$9:$W$9*($D$6:$W$6<=J$6)*(J$6-$D$6:$W$6<$D$9:$W$9)) -> 1.0519008e+10 | K18: =SUMPRODUCT($D$7:$W$7/$D$9:$W$9*($D$6:$W$6<=K$6)*(K$6-$D$6:$W$6<$D$9:$W$9)) -> 1.1803306e+10 | ... W18: =SUMPRODUCT($D$7:$W$7/$D$9:$W$9*($D$6:$W$6<=W$6)*(W$6-$D$6:$W$6<$D$9:$W$9)) -> 0 | X18: =SUM(D18:W18) -> 9.3398702e+10
B20: REPAVIMENTACIONES (SIN IVA) | D20: =+(FLUJO!C96*IMPUESTOS!$AA$29)/(1+IMPUESTOS!$AA$21)*(D$6<=FLUJO!$C$118) -> 0 | E20: =+(FLUJO!D96*IMPUESTOS!$AA$29)/(1+IMPUESTOS!$AA$21)*(E$6<=FLUJO!$C$118) -> 5.2341353e+09 | F20: =+(FLUJO!E96*IMPUESTOS!$AA$29)/(1+IMPUESTOS!$AA$21)*(F$6<=FLUJO!$C$118) -> 5.2341353e+09 | G20: =+(FLUJO!F96*IMPUESTOS!$AA$29)/(1+IMPUESTOS!$AA$21)*(G$6<=FLUJO!$C$118) -> 5.2341353e+09 | H20: =+(FLUJO!G96*IMPUESTOS!$AA$29)/(1+IMPUESTOS!$AA$21)*(H$6<=FLUJO!$C$118) -> 5.2341353e+09 | I20: =+(FLUJO!H96*IMPUESTOS!$AA$29)/(1+IMPUESTOS!$AA$21)*(I$6<=FLUJO!$C$118) -> 5.2341353e+09 | J20: =+(FLUJO!I96*IMPUESTOS!$AA$29)/(1+IMPUESTOS!$AA$21)*(J$6<=FLUJO!$C$118) -> 5.2341353e+09 | K20: =+(FLUJO!J96*IMPUESTOS!$AA$29)/(1+IMPUESTOS!$AA$21)*(K$6<=FLUJO!$C$118) -> 5.2341353e+09 | ... W20: =+(FLUJO!V96*IMPUESTOS!$AA$29)/(1+IMPUESTOS!$AA$21)*(W$6<=FLUJO!$C$118) -> 5.2341353e+09 | X20: =SUM(D20:W20) -> 9.944857e+10
B22: PERIODOS | D22: =MAX(1,MIN(CONTROL!$C$57,FLUJO!$C$118-D$6+1)) -> 5 | E22: =MAX(1,MIN(CONTROL!$C$57,FLUJO!$C$118-E$6+1)) -> 5 | F22: =MAX(1,MIN(CONTROL!$C$57,FLUJO!$C$118-F$6+1)) -> 5 | G22: =MAX(1,MIN(CONTROL!$C$57,FLUJO!$C$118-G$6+1)) -> 5 | H22: =MAX(1,MIN(CONTROL!$C$57,FLUJO!$C$118-H$6+1)) -> 5 | I22: =MAX(1,MIN(CONTROL!$C$57,FLUJO!$C$118-I$6+1)) -> 5 | J22: =MAX(1,MIN(CONTROL!$C$57,FLUJO!$C$118-J$6+1)) -> 5 | K22: =MAX(1,MIN(CONTROL!$C$57,FLUJO!$C$118-K$6+1)) -> 5 | ... W22: =MAX(1,MIN(CONTROL!$C$57,FLUJO!$C$118-W$6+1)) -> 1
B24: Cálculo integrado en la fila TOTAL (cada inversión se amortiza en sus períodos, sin pasar el fin de la concesión)
B45: TOTAL AMORTIZACIÓN REPAVIMENTACION | D45: =SUMPRODUCT($D$20:$W$20/$D$22:$W$22*($D$6:$W$6<=D$6)*(D$6-$D$6:$W$6<$D$22:$W$22)) -> 0 | E45: =SUMPRODUCT($D$20:$W$20/$D$22:$W$22*($D$6:$W$6<=E$6)*(E$6-$D$6:$W$6<$D$22:$W$22)) -> 1.0468271e+09 | F45: =SUMPRODUCT($D$20:$W$20/$D$22:$W$22*($D$6:$W$6<=F$6)*(F$6-$D$6:$W$6<$D$22:$W$22)) -> 2.0936541e+09 | G45: =SUMPRODUCT($D$20:$W$20/$D$22:$W$22*($D$6:$W$6<=G$6)*(G$6-$D$6:$W$6<$D$22:$W$22)) -> 3.1404812e+09 | H45: =SUMPRODUCT($D$20:$W$20/$D$22:$W$22*($D$6:$W$6<=H$6)*(H$6-$D$6:$W$6<$D$22:$W$22)) -> 4.1873082e+09 | I45: =SUMPRODUCT($D$20:$W$20/$D$22:$W$22*($D$6:$W$6<=I$6)*(I$6-$D$6:$W$6<$D$22:$W$22)) -> 5.2341353e+09 | J45: =SUMPRODUCT($D$20:$W$20/$D$22:$W$22*($D$6:$W$6<=J$6)*(J$6-$D$6:$W$6<$D$22:$W$22)) -> 5.2341353e+09 | K45: =SUMPRODUCT($D$20:$W$20/$D$22:$W$22*($D$6:$W$6<=K$6)*(K$6-$D$6:$W$6<$D$22:$W$22)) -> 5.2341353e+09 | ... W45: =SUMPRODUCT($D$20:$W$20/$D$22:$W$22*($D$6:$W$6<=W$6)*(W$6-$D$6:$W$6<$D$22:$W$22)) -> 1.1951276e+10 | X45: =SUM(D45:W45) -> 9.944857e+10
B48: AMORTIZACION ANNUAL TOTAL | D48: =+D18+D45 -> 3.2681702e+09 | E48: =+E18+E45 -> 4.3149973e+09 | F48: =+F18+F45 -> 7.013064e+09 | G48: =+G18+G45 -> 1.0811957e+10 | H48: =+H18+H45 -> 1.3081925e+10 | I48: =+I18+I45 -> 1.2817606e+10 | J48: =+J18+J45 -> 1.5753144e+10 | K48: =+K18+K45 -> 1.7037441e+10 | ... W48: =+W18+W45 -> 1.1951276e+10 | X48: =SUM(D48:W48) -> 1.9284727e+11
B50: AMORT. ANUAL ACUM. | D50: =D48+C50 -> 3.2681702e+09 | E50: =E48+D50 -> 7.5831676e+09 | F50: =F48+E50 -> 1.4596232e+10 | G50: =G48+F50 -> 2.5408189e+10 | H50: =H48+G50 -> 3.8490114e+10 | I50: =I48+H50 -> 5.130772e+10 | J50: =J48+I50 -> 6.7060863e+10 | K50: =K48+J50 -> 8.4098305e+10 | ... W50: =W48+V50 -> 1.9284727e+11
B53: AMORTIZACION de las Obras en el plazo restante de la Concesión y de las Repavimentaciones en su vida útil
B55: CONCEPTO | D55: Año 1 | E55: Año 2 | F55: Año 3 | G55: Año 4 | H55: Año 5 | I55: Año 6 | J55: Año 7 | K55: Año 8 | L55: Año 9 | M55: Año 10 | N55: Año 11 | O55: Año 12 | P55: Año 13 | Q55: Año 14 | R55: Año 15 | S55: Año 16 | T55: Año 17 | U55: Año 18 | V55: Año 19 | W55: Año 20 | X55: TOTAL
B57: INVERSIONES (SIN IVA) | D57: =+D7 -> 1.6340851e+10 | E57: =+E7 -> 0 | F57: =+F7 -> 8.2561983e+09 | G57: =+G7 -> 1.3760331e+10 | H57: =+H7 -> 6.1157025e+09 | I57: =+I7 -> 9.785124e+09 | J57: =+J7 -> 1.4677686e+10 | K57: =+K7 -> 1.4677686e+10 | ... W57: =+W7 -> 0 | X57: =SUM(D57:W57) -> 9.3398702e+10
B59: PERIODOS | D59: =MAX(1,FLUJO!$C$118-D$6+1) -> 20 | E59: =MAX(1,FLUJO!$C$118-E$6+1) -> 19 | F59: =MAX(1,FLUJO!$C$118-F$6+1) -> 18 | G59: =MAX(1,FLUJO!$C$118-G$6+1) -> 17 | H59: =MAX(1,FLUJO!$C$118-H$6+1) -> 16 | I59: =MAX(1,FLUJO!$C$118-I$6+1) -> 15 | J59: =MAX(1,FLUJO!$C$118-J$6+1) -> 14 | K59: =MAX(1,FLUJO!$C$118-K$6+1) -> 13 | ... W59: =MAX(1,FLUJO!$C$118-W$6+1) -> 1
B61: Cálculo integrado en la fila TOTAL (cada inversión se amortiza en sus períodos, sin pasar el fin de la concesión)
B68: TOTAL AMORTIZACIÓN OBRAS | D68: =SUMPRODUCT($D$57:$W$57/$D$59:$W$59*($D$6:$W$6<=D$6)*(D$6-$D$6:$W$6<$D$59:$W$59)) -> 8.1704256e+08 | E68: =SUMPRODUCT($D$57:$W$57/$D$59:$W$59*($D$6:$W$6<=E$6)*(E$6-$D$6:$W$6<$D$59:$W$59)) -> 8.1704256e+08 | F68: =SUMPRODUCT($D$57:$W$57/$D$59:$W$59*($D$6:$W$6<=F$6)*(F$6-$D$6:$W$6<$D$59:$W$59)) -> 1.2757202e+09 | G68: =SUMPRODUCT($D$57:$W$57/$D$59:$W$59*($D$6:$W$6<=G$6)*(G$6-$D$6:$W$6<$D$59:$W$59)) -> 2.0851515e+09 | H68: =SUMPRODUCT($D$57:$W$57/$D$59:$W$59*($D$6:$W$6<=H$6)*(H$6-$D$6:$W$6<$D$59:$W$59)) -> 2.4673829e+09 | I68: =SUMPRODUCT($D$57:$W$57/$D$59:$W$59*($D$6:$W$6<=I$6)*(I$6-$D$6:$W$6<$D$59:$W$59)) -> 3.1197245e+09 | J68: =SUMPRODUCT($D$57:$W$57/$D$59:$W$59*($D$6:$W$6<=J$6)*(J$6-$D$6:$W$6<$D$59:$W$59)) -> 4.1681306e+09 | K68: =SUMPRODUCT($D$57:$W$57/$D$59:$W$59*($D$6:$W$6<=K$6)*(K$6-$D$6:$W$6<$D$59:$W$59)) -> 5.2971834e+09 | ... W68: =SUMPRODUCT($D$57:$W$57/$D$59:$W$59*($D$6:$W$6<=W$6)*(W$6-$D$6:$W$6<$D$59:$W$59)) -> 6.1126104e+09 | X68: =SUM(D68:W68) -> 9.3398702e+10
B70: REPAVIMENTACIONES (SIN IVA) | D70: =+D20 -> 0 | E70: =+E20 -> 5.2341353e+09 | F70: =+F20 -> 5.2341353e+09 | G70: =+G20 -> 5.2341353e+09 | H70: =+H20 -> 5.2341353e+09 | I70: =+I20 -> 5.2341353e+09 | J70: =+J20 -> 5.2341353e+09 | K70: =+K20 -> 5.2341353e+09 | ... W70: =+W20 -> 5.2341353e+09 | X70: =SUM(D70:W70) -> 9.944857e+10
B72: PERIODOS | D72: =MAX(1,MIN(CONTROL!$C$57,FLUJO!$C$118-D$6+1)) -> 5 | E72: =MAX(1,MIN(CONTROL!$C$57,FLUJO!$C$118-E$6+1)) -> 5 | F72: =MAX(1,MIN(CONTROL!$C$57,FLUJO!$C$118-F$6+1)) -> 5 | G72: =MAX(1,MIN(CONTROL!$C$57,FLUJO!$C$118-G$6+1)) -> 5 | H72: =MAX(1,MIN(CONTROL!$C$57,FLUJO!$C$118-H$6+1)) -> 5 | I72: =MAX(1,MIN(CONTROL!$C$57,FLUJO!$C$118-I$6+1)) -> 5 | J72: =MAX(1,MIN(CONTROL!$C$57,FLUJO!$C$118-J$6+1)) -> 5 | K72: =MAX(1,MIN(CONTROL!$C$57,FLUJO!$C$118-K$6+1)) -> 5 | ... W72: =MAX(1,MIN(CONTROL!$C$57,FLUJO!$C$118-W$6+1)) -> 1
B74: Cálculo integrado en la fila TOTAL (cada inversión se amortiza en sus períodos, sin pasar el fin de la concesión)
B95: TOTAL AMORTIZACIÓN REPAVIMENTACION | D95: =SUMPRODUCT($D$70:$W$70/$D$72:$W$72*($D$6:$W$6<=D$6)*(D$6-$D$6:$W$6<$D$72:$W$72)) -> 0 | E95: =SUMPRODUCT($D$70:$W$70/$D$72:$W$72*($D$6:$W$6<=E$6)*(E$6-$D$6:$W$6<$D$72:$W$72)) -> 1.0468271e+09 | F95: =SUMPRODUCT($D$70:$W$70/$D$72:$W$72*($D$6:$W$6<=F$6)*(F$6-$D$6:$W$6<$D$72:$W$72)) -> 2.0936541e+09 | G95: =SUMPRODUCT($D$70:$W$70/$D$72:$W$72*($D$6:$W$6<=G$6)*(G$6-$D$6:$W$6<$D$72:$W$72)) -> 3.1404812e+09 | H95: =SUMPRODUCT($D$70:$W$70/$D$72:$W$72*($D$6:$W$6<=H$6)*(H$6-$D$6:$W$6<$D$72:$W$72)) -> 4.1873082e+09 | I95: =SUMPRODUCT($D$70:$W$70/$D$72:$W$72*($D$6:$W$6<=I$6)*(I$6-$D$6:$W$6<$D$72:$W$72)) -> 5.2341353e+09 | J95: =SUMPRODUCT($D$70:$W$70/$D$72:$W$72*($D$6:$W$6<=J$6)*(J$6-$D$6:$W$6<$D$72:$W$72)) -> 5.2341353e+09 | K95: =SUMPRODUCT($D$70:$W$70/$D$72:$W$72*($D$6:$W$6<=K$6)*(K$6-$D$6:$W$6<$D$72:$W$72)) -> 5.2341353e+09 | ... W95: =SUMPRODUCT($D$70:$W$70/$D$72:$W$72*($D$6:$W$6<=W$6)*(W$6-$D$6:$W$6<$D$72:$W$72)) -> 1.1951276e+10 | X95: =SUM(D95:W95) -> 9.944857e+10
B98: AMORTIZACION ANNUAL TOTAL | D98: =+D68+D95 -> 8.1704256e+08 | E98: =+E68+E95 -> 1.8638696e+09 | F98: =+F68+F95 -> 3.3693744e+09 | G98: =+G68+G95 -> 5.2256326e+09 | H98: =+H68+H95 -> 6.6546911e+09 | I98: =+I68+I95 -> 8.3538597e+09 | J98: =+J68+J95 -> 9.4022659e+09 | K98: =+K68+K95 -> 1.0531319e+10 | ... W98: =+W68+W95 -> 1.8063886e+10 | X98: =SUM(D98:W98) -> 1.9284727e+11
B100: AMORT. ANUAL ACUM. | D100: =D98+C100 -> 8.1704256e+08 | E100: =E98+D100 -> 2.6809122e+09 | F100: =F98+E100 -> 6.0502865e+09 | G100: =G98+F100 -> 1.1275919e+10 | H100: =H98+G100 -> 1.793061e+10 | I100: =I98+H100 -> 2.628447e+10 | J100: =J98+I100 -> 3.5686736e+10 | K100: =K98+J100 -> 4.6218055e+10 | ... W100: =W98+V100 -> 1.9284727e+11
B103: AMORTIZACION INSTANTANEA (SE AMORTIZA EL 100% DE SU VALOR EL MISMO AÑO DE EJECUCIÓN)
B105: CONCEPTO | D105: Año 1 | E105: Año 2 | F105: Año 3 | G105: Año 4 | H105: Año 5 | I105: Año 6 | J105: Año 7 | K105: Año 8 | L105: Año 9 | M105: Año 10 | N105: Año 11 | O105: Año 12 | P105: Año 13 | Q105: Año 14 | R105: Año 15 | S105: Año 16 | T105: Año 17 | U105: Año 18 | V105: Año 19 | W105: Año 20 | X105: TOTAL
B107: INVERSIONES (SIN IVA) | D107: =+D57 -> 1.6340851e+10 | E107: =+E57 -> 0 | F107: =+F57 -> 8.2561983e+09 | G107: =+G57 -> 1.3760331e+10 | H107: =+H57 -> 6.1157025e+09 | I107: =+I57 -> 9.785124e+09 | J107: =+J57 -> 1.4677686e+10 | K107: =+K57 -> 1.4677686e+10 | ... W107: =+W57 -> 0 | X107: =SUM(D107:W107) -> 9.3398702e+10
B109: PERIODOS | D109: =1 -> 1 | E109: =1 -> 1 | F109: =1 -> 1 | G109: =1 -> 1 | H109: =1 -> 1 | I109: =1 -> 1 | J109: =1 -> 1 | K109: =1 -> 1 | ... W109: =1 -> 1
B111: Cálculo integrado en la fila TOTAL (cada inversión se amortiza en sus períodos, sin pasar el fin de la concesión)
B118: TOTAL AMORTIZACIÓN OBRAS | D118: =SUMPRODUCT($D$107:$W$107/$D$109:$W$109*($D$6:$W$6<=D$6)*(D$6-$D$6:$W$6<$D$109:$W$109)) -> 1.6340851e+10 | E118: =SUMPRODUCT($D$107:$W$107/$D$109:$W$109*($D$6:$W$6<=E$6)*(E$6-$D$6:$W$6<$D$109:$W$109)) -> 0 | F118: =SUMPRODUCT($D$107:$W$107/$D$109:$W$109*($D$6:$W$6<=F$6)*(F$6-$D$6:$W$6<$D$109:$W$109)) -> 8.2561983e+09 | G118: =SUMPRODUCT($D$107:$W$107/$D$109:$W$109*($D$6:$W$6<=G$6)*(G$6-$D$6:$W$6<$D$109:$W$109)) -> 1.3760331e+10 | H118: =SUMPRODUCT($D$107:$W$107/$D$109:$W$109*($D$6:$W$6<=H$6)*(H$6-$D$6:$W$6<$D$109:$W$109)) -> 6.1157025e+09 | I118: =SUMPRODUCT($D$107:$W$107/$D$109:$W$109*($D$6:$W$6<=I$6)*(I$6-$D$6:$W$6<$D$109:$W$109)) -> 9.785124e+09 | J118: =SUMPRODUCT($D$107:$W$107/$D$109:$W$109*($D$6:$W$6<=J$6)*(J$6-$D$6:$W$6<$D$109:$W$109)) -> 1.4677686e+10 | K118: =SUMPRODUCT($D$107:$W$107/$D$109:$W$109*($D$6:$W$6<=K$6)*(K$6-$D$6:$W$6<$D$109:$W$109)) -> 1.4677686e+10 | ... W118: =SUMPRODUCT($D$107:$W$107/$D$109:$W$109*($D$6:$W$6<=W$6)*(W$6-$D$6:$W$6<$D$109:$W$109)) -> 0 | X118: =SUM(D118:W118) -> 9.3398702e+10
B120: REPAVIMENTACIONES (SIN IVA) | D120: =+D70 -> 0 | E120: =+E70 -> 5.2341353e+09 | F120: =+F70 -> 5.2341353e+09 | G120: =+G70 -> 5.2341353e+09 | H120: =+H70 -> 5.2341353e+09 | I120: =+I70 -> 5.2341353e+09 | J120: =+J70 -> 5.2341353e+09 | K120: =+K70 -> 5.2341353e+09 | ... W120: =+W70 -> 5.2341353e+09 | X120: =SUM(D120:W120) -> 9.944857e+10
B122: PERIODOS | D122: =1 -> 1 | E122: =1 -> 1 | F122: =1 -> 1 | G122: =1 -> 1 | H122: =1 -> 1 | I122: =1 -> 1 | J122: =1 -> 1 | K122: =1 -> 1 | ... W122: =1 -> 1
B124: Cálculo integrado en la fila TOTAL (cada inversión se amortiza en sus períodos, sin pasar el fin de la concesión)
B145: TOTAL AMORTIZACIÓN REPAVIMENTACION | D145: =SUMPRODUCT($D$120:$W$120/$D$122:$W$122*($D$6:$W$6<=D$6)*(D$6-$D$6:$W$6<$D$122:$W$122)) -> 0 | E145: =SUMPRODUCT($D$120:$W$120/$D$122:$W$122*($D$6:$W$6<=E$6)*(E$6-$D$6:$W$6<$D$122:$W$122)) -> 5.2341353e+09 | F145: =SUMPRODUCT($D$120:$W$120/$D$122:$W$122*($D$6:$W$6<=F$6)*(F$6-$D$6:$W$6<$D$122:$W$122)) -> 5.2341353e+09 | G145: =SUMPRODUCT($D$120:$W$120/$D$122:$W$122*($D$6:$W$6<=G$6)*(G$6-$D$6:$W$6<$D$122:$W$122)) -> 5.2341353e+09 | H145: =SUMPRODUCT($D$120:$W$120/$D$122:$W$122*($D$6:$W$6<=H$6)*(H$6-$D$6:$W$6<$D$122:$W$122)) -> 5.2341353e+09 | I145: =SUMPRODUCT($D$120:$W$120/$D$122:$W$122*($D$6:$W$6<=I$6)*(I$6-$D$6:$W$6<$D$122:$W$122)) -> 5.2341353e+09 | J145: =SUMPRODUCT($D$120:$W$120/$D$122:$W$122*($D$6:$W$6<=J$6)*(J$6-$D$6:$W$6<$D$122:$W$122)) -> 5.2341353e+09 | K145: =SUMPRODUCT($D$120:$W$120/$D$122:$W$122*($D$6:$W$6<=K$6)*(K$6-$D$6:$W$6<$D$122:$W$122)) -> 5.2341353e+09 | ... W145: =SUMPRODUCT($D$120:$W$120/$D$122:$W$122*($D$6:$W$6<=W$6)*(W$6-$D$6:$W$6<$D$122:$W$122)) -> 5.2341353e+09 | X145: =SUM(D145:W145) -> 9.944857e+10
B148: AMORTIZACION ANNUAL TOTAL | D148: =+D118+D145 -> 1.6340851e+10 | E148: =+E118+E145 -> 5.2341353e+09 | F148: =+F118+F145 -> 1.3490334e+10 | G148: =+G118+G145 -> 1.8994466e+10 | H148: =+H118+H145 -> 1.1349838e+10 | I148: =+I118+I145 -> 1.5019259e+10 | J148: =+J118+J145 -> 1.9911821e+10 | K148: =+K118+K145 -> 1.9911821e+10 | ... W148: =+W118+W145 -> 5.2341353e+09 | X148: =SUM(D148:W148) -> 1.9284727e+11
B150: AMORT. ANUAL ACUM. | D150: =D148+C150 -> 1.6340851e+10 | E150: =E148+D150 -> 2.1574987e+10 | F150: =F148+E150 -> 3.506532e+10 | G150: =G148+F150 -> 5.4059786e+10 | H150: =H148+G150 -> 6.5409624e+10 | I150: =I148+H150 -> 8.0428883e+10 | J150: =J148+I150 -> 1.003407e+11 | K150: =K148+J150 -> 1.2025253e+11 | ... W150: =W148+V150 -> 1.9284727e+11

Sheet INPUTS
A1: FLUJO CAPEX - OPEX
A2: AÑO | B2: Año 2027 | C2: Año 2028 | D2: Año 2029 | E2: Año 2030 | F2: Año 2031 | G2: Año 2032 | H2: Año 2033 | I2: Año 2034 | J2: Año 2035 | K2: Año 2036 | L2: Año 2037 | M2: Año 2038 | N2: Año 2039 | O2: Año 2040 | P2: Año 2041 | Q2: Año 2042 | R2: Año 2043 | S2: Año 2044 | T2: Año 2045 | U2: Año 2046 | V2: TOTALES
B3: 1 | C3: 2 | D3: 3 | E3: 4 | F3: 5 | G3: 6 | H3: 7 | I3: 8 | J3: 9 | K3: 10 | L3: 11 | M3: 12 | N3: 13 | O3: 14 | P3: 15 | Q3: 16 | R3: 17 | S3: 18 | T3: 19 | U3: 20
A4: OBRAS | B4: 19772430000 | C4: 0 | D4: 9990000000 | E4: 16650000000 | F4: 7400000000 | G4: 11840000000 | H4: 17760000000 | I4: 17760000000 | J4: 11840000000 | K4: 0 | L4: 0 | M4: 0 | N4: 0 | O4: 0 | P4: 0 | Q4: 0 | R4: 0 | S4: 0 | T4: 0 | U4: 0
B5: 1 | C5: 1 | D5: 1 | E5: 1 | F5: 1 | G5: 1 | H5: 1 | I5: 1 | J5: 1 | K5: 1 | L5: 1 | M5: 1 | N5: 1 | O5: 1 | P5: 1 | Q5: 1 | R5: 1 | S5: 1 | T5: 1 | U5: 1
B6: 1 | C6: 1 | D6: 1 | E6: 1 | F6: 1 | G6: 1 | H6: 1 | I6: 1 | J6: 1 | K6: 1 | L6: 1 | M6: 1 | N6: 1 | O6: 1 | P6: 1 | Q6: 1 | R6: 1 | S6: 1 | T6: 1 | U6: 1
B7: =+B4*B5*B6 -> 19772430000 | C7: =+C4*C5*C6 -> 0 | D7: =+D4*D5*D6 -> 9990000000 | E7: =+E4*E5*E6 -> 16650000000 | F7: =+F4*F5*F6 -> 7400000000 | G7: =+G4*G5*G6 -> 11840000000 | H7: =+H4*H5*H6 -> 17760000000 | I7: =+I4*I5*I6 -> 17760000000 | ... U7: =+U4*U5*U6 -> 0 | V7: =SUM(B7:U7) -> 113012430000
A8: REPAVIMENTACION | B8: 6.3333037e+09 | C8: 6.3333037e+09 | D8: 6.3333037e+09 | E8: 6.3333037e+09 | F8: 6.3333037e+09 | G8: 6.3333037e+09 | H8: 6.3333037e+09 | I8: 6.3333037e+09 | J8: 6.3333037e+09 | K8: 6.3333037e+09 | L8: 6.3333037e+09 | M8: 6.3333037e+09 | N8: 6.3333037e+09 | O8: 6.3333037e+09 | P8: 6.3333037e+09 | Q8: 6.3333037e+09 | R8: 6.3333037e+09 | S8: 6.3333037e+09 | T8: 6.3333037e+09 | U8: 6.3333037e+09
B9: 0 | C9: 1 | D9: 1 | E9: 1 | F9: 1 | G9: 1 | H9: 1 | I9: 1 | J9: 1 | K9: 1 | L9: 1 | M9: 1 | N9: 1 | O9: 1 | P9: 1 | Q9: 1 | R9: 1 | S9: 1 | T9: 1 | U9: 1
B10: 1 | C10: 1 | D10: 1 | E10: 1 | F10: 1 | G10: 1 | H10: 1 | I10: 1 | J10: 1 | K10: 1 | L10: 1 | M10: 1 | N10: 1 | O10: 1 | P10: 1 | Q10: 1 | R10: 1 | S10: 1 | T10: 1 | U10: 1
B11: =+B8*B9*B10 -> 0 | C11: =+C8*C9*C10 -> 6.3333037e+09 | D11: =+D8*D9*D10 -> 6.3333037e+09 | E11: =+E8*E9*E10 -> 6.3333037e+09 | F11: =+F8*F9*F10 -> 6.3333037e+09 | G11: =+G8*G9*G10 -> 6.3333037e+09 | H11: =+H8*H9*H10 -> 6.3333037e+09 | I11: =+I8*I9*I10 -> 6.3333037e+09 | ... U11: =+U8*U9*U10 -> 6.3333037e+09 | V11: =SUM(B11:U11) -> 1.2033277e+11
A12: TOTAL OBRAS | B12: =+B7+B11 -> 19772430000 | C12: =+C7+C11 -> 6.3333037e+09 | D12: =+D7+D11 -> 16323303690 | E12: =+E7+E11 -> 22983303690 | F12: =+F7+F11 -> 13733303690 | G12: =+G7+G11 -> 18173303690 | H12: =+H7+H11 -> 24093303690 | I12: =+I7+I11 -> 24093303690 | ... U12: =+U7+U11 -> 6.3333037e+09 | V12: =SUM(B12:U12) -> 233345200110
A13: OPERACIÓN | B13: 1598400000 | C13: 1598400000 | D13: 1598400000 | E13: 1598400000 | F13: 1598400000 | G13: 1598400000 | H13: 1598400000 | I13: 1598400000 | J13: 1598400000 | K13: 1598400000 | L13: 1598400000 | M13: 1598400000 | N13: 1598400000 | O13: 1598400000 | P13: 1598400000 | Q13: 1598400000 | R13: 1598400000 | S13: 1598400000 | T13: 1598400000 | U13: 1598400000
B14: 1 | C14: 1 | D14: 1 | E14: 1 | F14: 1 | G14: 1 | H14: 1 | I14: 1 | J14: 1 | K14: 1 | L14: 1 | M14: 1 | N14: 1 | O14: 1 | P14: 1 | Q14: 1 | R14: 1 | S14: 1 | T14: 1 | U14: 1
B15: 1 | C15: 1 | D15: 1 | E15: 1 | F15: 1 | G15: 1 | H15: 1 | I15: 1 | J15: 1 | K15: 1 | L15: 1 | M15: 1 | N15: 1 | O15: 1 | P15: 1 | Q15: 1 | R15: 1 | S15: 1 | T15: 1 | U15: 1
B16: =+B13*B14*B15 -> 1598400000 | C16: =+C13*C14*C15 -> 1598400000 | D16: =+D13*D14*D15 -> 1598400000 | E16: =+E13*E14*E15 -> 1598400000 | F16: =+F13*F14*F15 -> 1598400000 | G16: =+G13*G14*G15 -> 1598400000 | H16: =+H13*H14*H15 -> 1598400000 | I16: =+I13*I14*I15 -> 1598400000 | ... U16: =+U13*U14*U15 -> 1598400000 | V16: =SUM(B16:U16) -> 31968000000
A17: MANTENIMIENTO | B17: 7080712200 | C17: 7080712200 | D17: 7080712200 | E17: 7080712200 | F17: 7080712200 | G17: 7080712200 | H17: 7080712200 | I17: 7080712200 | J17: 7080712200 | K17: 7080712200 | L17: 7080712200 | M17: 7080712200 | N17: 7080712200 | O17: 7080712200 | P17: 7080712200 | Q17: 7080712200 | R17: 7080712200 | S17: 7080712200 | T17: 7080712200 | U17: 7080712200
B18: 0.3 | C18: 0.3 | D18: 0.5 | E18: 1 | F18: 1 | G18: 1 | H18: 1 | I18: 1 | J18: 1 | K18: 1 | L18: 1 | M18: 1 | N18: 1 | O18: 1 | P18: 1 | Q18: 1 | R18: 1 | S18: 1 | T18: 1 | U18: 1
B19: 1 | C19: 1 | D19: 1 | E19: 1 | F19: 1 | G19: 1 | H19: 1 | I19: 1 | J19: 1 | K19: 1 | L19: 1 | M19: 1 | N19: 1 | O19: 1 | P19: 1 | Q19: 1 | R19: 1 | S19: 1 | T19: 1 | U19: 1
B20: =+B17*B18*B19 -> 2124213660 | C20: =+C17*C18*C19 -> 2124213660 | D20: =+D17*D18*D19 -> 3540356100 | E20: =+E17*E18*E19 -> 7080712200 | F20: =+F17*F18*F19 -> 7080712200 | G20: =+G17*G18*G19 -> 7080712200 | H20: =+H17*H18*H19 -> 7080712200 | I20: =+I17*I18*I19 -> 7080712200 | ... U20: =+U17*U18*U19 -> 7080712200 | V20: =SUM(B20:U20) -> 128160890820
A21: SERVICIOS AL USUARIO | B21: 524497200 | C21: 524497200 | D21: 524497200 | E21: 524497200 | F21: 524497200 | G21: 524497200 | H21: 524497200 | I21: 524497200 | J21: 524497200 | K21: 524497200 | L21: 524497200 | M21: 524497200 | N21: 524497200 | O21: 524497200 | P21: 524497200 | Q21: 524497200 | R21: 524497200 | S21: 524497200 | T21: 524497200 | U21: 524497200
B22: 1 | C22: 1 | D22: 1 | E22: 1 | F22: 1 | G22: 1 | H22: 1 | I22: 1 | J22: 1 | K22: 1 | L22: 1 | M22: 1 | N22: 1 | O22: 1 | P22: 1 | Q22: 1 | R22: 1 | S22: 1 | T22: 1 | U22: 1
B23: 1 | C23: 1 | D23: 1 | E23: 1 | F23: 1 | G23: 1 | H23: 1 | I23: 1 | J23: 1 | K23: 1 | L23: 1 | M23: 1 | N23: 1 | O23: 1 | P23: 1 | Q23: 1 | R23: 1 | S23: 1 | T23: 1 | U23: 1
B24: =+B21*B22*B23 -> 524497200 | C24: =+C21*C22*C23 -> 524497200 | D24: =+D21*D22*D23 -> 524497200 | E24: =+E21*E22*E23 -> 524497200 | F24: =+F21*F22*F23 -> 524497200 | G24: =+G21*G22*G23 -> 524497200 | H24: =+H21*H22*H23 -> 524497200 | I24: =+I21*I22*I23 -> 524497200 | ... U24: =+U21*U22*U23 -> 524497200 | V24: =SUM(B24:U24) -> 10489944000
A25: ADMINISTRACION | B25: 1346800000 | C25: 1346800000 | D25: 1346800000 | E25: 1346800000 | F25: 1346800000 | G25: 1346800000 | H25: 1346800000 | I25: 1346800000 | J25: 1346800000 | K25: 1346800000 | L25: 1346800000 | M25: 1346800000 | N25: 1346800000 | O25: 1346800000 | P25: 1346800000 | Q25: 1346800000 | R25: 1346800000 | S25: 1346800000 | T25: 1346800000 | U25: 1346800000
B26: 1 | C26: 1 | D26: 1 | E26: 1 | F26: 1 | G26: 1 | H26: 1 | I26: 1 | J26: 1 | K26: 1 | L26: 1 | M26: 1 | N26: 1 | O26: 1 | P26: 1 | Q26: 1 | R26: 1 | S26: 1 | T26: 1 | U26: 1
B27: 1 | C27: 1 | D27: 1 | E27: 1 | F27: 1 | G27: 1 | H27: 1 | I27: 1 | J27: 1 | K27: 1 | L27: 1 | M27: 1 | N27: 1 | O27: 1 | P27: 1 | Q27: 1 | R27: 1 | S27: 1 | T27: 1 | U27: 1
B28: =+B25*B26*B27 -> 1346800000 | C28: =+C25*C26*C27 -> 1346800000 | D28: =+D25*D26*D27 -> 1346800000 | E28: =+E25*E26*E27 -> 1346800000 | F28: =+F25*F26*F27 -> 1346800000 | G28: =+G25*G26*G27 -> 1346800000 | H28: =+H25*H26*H27 -> 1346800000 | I28: =+I25*I26*I27 -> 1346800000 | ... U28: =+U25*U26*U27 -> 1346800000 | V28: =SUM(B28:U28) -> 26936000000
A29: TOTAL OPERACIÓN Y MANTENIMIENTO | B29: =+B16+B20+B24+B28 -> 5593910860 | C29: =+C16+C20+C24+C28 -> 5593910860 | D29: =+D16+D20+D24+D28 -> 7010053300 | E29: =+E16+E20+E24+E28 -> 10550409400 | F29: =+F16+F20+F24+F28 -> 10550409400 | G29: =+G16+G20+G24+G28 -> 10550409400 | H29: =+H16+H20+H24+H28 -> 10550409400 | I29: =+I16+I20+I24+I28 -> 10550409400 | ... U29: =+U16+U20+U24+U28 -> 10550409400 | V29: =SUM(B29:U29) -> 197554834820

Sheet OPEX
B2: =+FLUJO!B4 -> 1 de junio 2026 | E2: =+FLUJO!C4 -> 2027 | F2: =+FLUJO!D4 -> 2028 | G2: =+FLUJO!E4 -> 2029 | H2: =+FLUJO!F4 -> 2030 | I2: =+FLUJO!G4 -> 2031 | J2: =+FLUJO!H4 -> 2032 | K2: =+FLUJO!I4 -> 2033 | L2: =+FLUJO!J4 -> 2034 | ... X2: =+FLUJO!V4 -> 2046
B3: =+CONTROL!B2 -> TIR Nominal (con IVA) | E3: =+FLUJO!C5 -> 46388 | F3: =+FLUJO!D5 -> 46753 | G3: =+FLUJO!E5 -> 47119 | H3: =+FLUJO!F5 -> 47484 | I3: =+FLUJO!G5 -> 47849 | J3: =+FLUJO!H5 -> 48214 | K3: =+FLUJO!I5 -> 48580 | L3: =+FLUJO!J5 -> 48945 | ... X3: =+FLUJO!V5 -> 53328
B4: =+FLUJO!B6 -> 2.2128475 | E4: =+FLUJO!C6 -> 46752 | F4: =+FLUJO!D6 -> 47118 | G4: =+FLUJO!E6 -> 47483 | H4: =+FLUJO!F6 -> 47848 | I4: =+FLUJO!G6 -> 48213 | J4: =+FLUJO!H6 -> 48579 | K4: =+FLUJO!I6 -> 48944 | L4: =+FLUJO!J6 -> 49309 | ... X4: =+FLUJO!V6 -> 53692
B6: Año de Concesión | E6: 1 | F6: 2 | G6: 3 | H6: 4 | I6: 5 | J6: 6 | K6: 7 | L6: 8 | M6: 9 | N6: 10 | O6: 11 | P6: 12 | Q6: 13 | R6: 14 | S6: 15 | T6: 16 | U6: 17 | V6: 18 | W6: 19 | X6: 20
B7: Días del Año | E7: =+E4-E3+1 -> 365 | F7: =+F4-F3+1 -> 366 | G7: =+G4-G3+1 -> 365 | H7: =+H4-H3+1 -> 365 | I7: =+I4-I3+1 -> 365 | J7: =+J4-J3+1 -> 366 | K7: =+K4-K3+1 -> 365 | L7: =+L4-L3+1 -> 365 | ... X7: =+X4-X3+1 -> 365
B8: Días del Año (Operación) | E8: =+-E3+E4+1 -> 365 | F8: =+F7 -> 366 | G8: =+G7 -> 365 | H8: =+H7 -> 365 | I8: =+I7 -> 365 | J8: =+J7 -> 366 | K8: =+K7 -> 365 | L8: =+L7 -> 365 | M8: =+M7 -> 365 | ... X8: =+X7 -> 365
B9: Días del Año (Construcción) | E9: =+E8 -> 365 | F9: =+F8 -> 366 | G9: =+G8 -> 365 | H9: =+H8 -> 365 | I9: =+I8 -> 365 | J9: =+J8 -> 366 | K9: =+K8 -> 365 | L9: =+L8 -> 365 | ... X9: =+X8 -> 365
B10: Factor de Ingresos | E10: =+HIPOTESIS!C11 -> 1 | F10: =+HIPOTESIS!D11 -> 1 | G10: =+HIPOTESIS!E11 -> 1 | H10: =+HIPOTESIS!F11 -> 1 | I10: =+HIPOTESIS!G11 -> 1 | J10: =+HIPOTESIS!H11 -> 1 | K10: =+HIPOTESIS!I11 -> 1 | L10: =+HIPOTESIS!J11 -> 1 | ... X10: =+HIPOTESIS!V11 -> 1
B11: Factor de Operación | E11: =+HIPOTESIS!C12 -> 1 | F11: =+HIPOTESIS!D12 -> 1 | G11: =+HIPOTESIS!E12 -> 1 | H11: =+HIPOTESIS!F12 -> 1 | I11: =+HIPOTESIS!G12 -> 1 | J11: =+HIPOTESIS!H12 -> 1 | K11: =+HIPOTESIS!I12 -> 1 | L11: =+HIPOTESIS!J12 -> 1 | ... X11: =+HIPOTESIS!V12 -> 1
B12: Factor de Construcción | E12: =+HIPOTESIS!C13 -> 1 | F12: =+HIPOTESIS!D13 -> 1 | G12: =+HIPOTESIS!E13 -> 1 | H12: =+HIPOTESIS!F13 -> 1 | I12: =+HIPOTESIS!G13 -> 1 | J12: =+HIPOTESIS!H13 -> 1 | K12: =+HIPOTESIS!I13 -> 1 | L12: =+HIPOTESIS!J13 -> 1 | ... X12: =+HIPOTESIS!V13 -> 1
B14: Sensibilidad CyM | C14: =+CONTROL!C32 -> 0 | E14: =+C14 -> 0 | F14: =+E14 -> 0 | G14: =+F14 -> 0 | H14: =+G14 -> 0 | I14: =+H14 -> 0 | J14: =+I14 -> 0 | K14: =+J14 -> 0 | L14: =+K14 -> 0 | M14: =+L14 -> 0 | ... X14: =+W14 -> 0
B15: Sensibilidad At. al Usuario | C15: =+CONTROL!C33 -> 0 | E15: =+C15 -> 0 | F15: =+E15 -> 0 | G15: =+F15 -> 0 | H15: =+G15 -> 0 | I15: =+H15 -> 0 | J15: =+I15 -> 0 | K15: =+J15 -> 0 | L15: =+K15 -> 0 | M15: =+L15 -> 0 | ... X15: =+W15 -> 0
B16: Sensibilidad Administración | C16: =+CONTROL!C34 -> 0 | E16: =+C16 -> 0 | F16: =+E16 -> 0 | G16: =+F16 -> 0 | H16: =+G16 -> 0 | I16: =+H16 -> 0 | J16: =+I16 -> 0 | K16: =+J16 -> 0 | L16: =+K16 -> 0 | M16: =+L16 -> 0 | ... X16: =+W16 -> 0
B17: Sensibilidad Explotación | C17: =+CONTROL!C35 -> 0 | E17: =+C17 -> 0 | F17: =+E17 -> 0 | G17: =+F17 -> 0 | H17: =+G17 -> 0 | I17: =+H17 -> 0 | J17: =+I17 -> 0 | K17: =+J17 -> 0 | L17: =+K17 -> 0 | M17: =+L17 -> 0 | ... X17: =+W17 -> 0
Y18: TOTAL
B19: Conservación y Mantenimiento | E19: =+INPUTS!B20*(1+E14) -> 2124213660 | F19: =+INPUTS!C20*(1+F14) -> 2124213660 | G19: =+INPUTS!D20*(1+G14) -> 3540356100 | H19: =+INPUTS!E20*(1+H14) -> 7080712200 | I19: =+INPUTS!F20*(1+I14) -> 7080712200 | J19: =+INPUTS!G20*(1+J14) -> 7080712200 | K19: =+INPUTS!H20*(1+K14) -> 7080712200 | L19: =+INPUTS!I20*(1+L14) -> 7080712200 | ... X19: =+INPUTS!U20*(1+X14) -> 7080712200 | Y19: =+SUM(E19:X19) -> 128160890820
B20: Atención al Usuario | E20: =+INPUTS!B24*(1+E15) -> 524497200 | F20: =+INPUTS!C24*(1+F15) -> 524497200 | G20: =+INPUTS!D24*(1+G15) -> 524497200 | H20: =+INPUTS!E24*(1+H15) -> 524497200 | I20: =+INPUTS!F24*(1+I15) -> 524497200 | J20: =+INPUTS!G24*(1+J15) -> 524497200 | K20: =+INPUTS!H24*(1+K15) -> 524497200 | L20: =+INPUTS!I24*(1+L15) -> 524497200 | ... X20: =+INPUTS!U24*(1+X15) -> 524497200 | Y20: =+SUM(E20:X20) -> 10489944000
B21: Administración | E21: =+INPUTS!B28*(1+E16) -> 1346800000 | F21: =+INPUTS!C28*(1+F16) -> 1346800000 | G21: =+INPUTS!D28*(1+G16) -> 1346800000 | H21: =+INPUTS!E28*(1+H16) -> 1346800000 | I21: =+INPUTS!F28*(1+I16) -> 1346800000 | J21: =+INPUTS!G28*(1+J16) -> 1346800000 | K21: =+INPUTS!H28*(1+K16) -> 1346800000 | L21: =+INPUTS!I28*(1+L16) -> 1346800000 | ... X21: =+INPUTS!U28*(1+X16) -> 1346800000 | Y21: =+SUM(E21:X21) -> 26936000000
B22: Explotación | E22: =+INPUTS!B16*(1+E17) -> 1598400000 | F22: =+INPUTS!C16*(1+F17) -> 1598400000 | G22: =+INPUTS!D16*(1+G17) -> 1598400000 | H22: =+INPUTS!E16*(1+H17) -> 1598400000 | I22: =+INPUTS!F16*(1+I17) -> 1598400000 | J22: =+INPUTS!G16*(1+J17) -> 1598400000 | K22: =+INPUTS!H16*(1+K17) -> 1598400000 | L22: =+INPUTS!I16*(1+L17) -> 1598400000 | ... X22: =+INPUTS!U16*(1+X17) -> 1598400000 | Y22: =+SUM(E22:X22) -> 31968000000
B23: OPEX TOTAL | E23: =SUM(E19:E22) -> 5593910860 | F23: =SUM(F19:F22) -> 5593910860 | G23: =SUM(G19:G22) -> 7010053300 | H23: =SUM(H19:H22) -> 10550409400 | I23: =SUM(I19:I22) -> 10550409400 | J23: =SUM(J19:J22) -> 10550409400 | K23: =SUM(K19:K22) -> 10550409400 | L23: =SUM(L19:L22) -> 10550409400 | ... S23: =SUM(S19:S22) -> 10550409400 | T23: =IF(CONTROL!$C$12=2,SUM(T19:T22),0) -> 10550409400 | U23: =IF(CONTROL!$C$12=2,SUM(U19:U22),0) -> 10550409400 | V23: =IF(CONTROL!$C$12=2,SUM(V19:V22),0) -> 10550409400 | W23: =IF(CONTROL!$C$12=2,SUM(W19:W22),0) -> 10550409400 | X23: =IF(CONTROL!$C$12=2,SUM(X19:X22),0) -> 10550409400 | Y23: =+SUM(E23:X23) -> 197554834820

Sheet PRESTAMO 
C2: Saldo a amortizar (con gracia incluye interés capitalizado del año 1) | D2: =IF(CONTROL!G32="NO",CONTROL!G24,CONTROL!G24*(1+CONTROL!G26)) -> 2.5317954e+10 | F2: Resumen:
C3: TNA (30/360) | D3: =+CONTROL!G26 -> 0.085 | F3: Valor préstamo | G3: =D2 -> 2.5317954e+10
C4: Años | D4: =+D8 -> 6 | F4: Suma de Cuotas | G4: =SUM($D$13:$D$399) -> 3.3360013e+10
C5: Frecuencia de Pago | D5: Anual | F5: Suma de Interés | G5: =SUM($E$13:$E$399) -> 8.0420584e+09
C6: Interés equivalente | D6: =D3/D7 -> 0.085
C7: N° de pagos por año | D7: 1
C8: N° Total de Cuotas | D8: =+CONTROL!G28 -> 6
C9: Gastos Administrativos | D9: =+CONTROL!G24*C10 -> 2.333452e+08
C10: 0.01
C11: Número de Cuota | D11: CUOTA A PAGAR | E11: INTERÉS | F11: CAPITAL AMORTIZADO | G11: CAPITAL VIVO | H11: IVA contenido en intereses (informativo) | J11: Art. 85 de la Ley del Impuesto a las Ganancias. En el caso de los sujetos comprendidos en el artículo 53, los intereses de deudas de carácter financiero —excluyéndose, en consecuencia, las deudas generadas por adquisiciones de bienes, locaciones y prestaciones de servicios relacionados con el giro del negocio— contraídos con sujetos, residentes o no en la REPÚBLICA ARGENTINA, vinculados en los términos del artículo 18 de esta ley, serán deducibles del balance impositivo al que corresponda su imputación, no pudiendo superar tal deducción el monto anual que al respecto establezca el PODER EJECUTIVO NACIONAL o el equivalente al TREINTA POR CIENTO (30 %) de la ganancia neta del ejercicio que resulte antes de deducir tanto los intereses a los que alude este párrafo como las amortizaciones previstas en esta ley, el que resulte mayor.
C12: 0 | G12: =D2 -> 2.5317954e+10
C13: =IF(OR(C12=$D$8,C12=""),"",IF(ISNUMBER(C12),C12+1,1)) -> 1 | D13: =IF(C13>$D$8,"",IF(CONTROL!$G$29=1,PMT($D$6,$D$8,$D$2)*-1,'PRESTAMO '!E13+'PRESTAMO '!F13)) -> 5.5600021e+09 | E13: =IF(C13>$D$8,"",$D$6*G12) -> 2.1520261e+09 | F13: =IF(C13>$D$8,"",IF(CONTROL!$G$29=1,D13-E13,'PRESTAMO '!$D$2/'PRESTAMO '!$D$8)) -> 3.407976e+09 | G13: =IF(C13>$D$8,"",G12-F13) -> 2.1909978e+10 | H13: =+(E13*0.21)/1.21 -> 3.7349213e+08
C14: =IF(OR(C13=$D$8,C13=""),"",IF(ISNUMBER(C13),C13+1,1)) -> 2 | D14: =IF(C14>$D$8,"",IF(CONTROL!$G$29=1,PMT($D$6,$D$8,$D$2)*-1,'PRESTAMO '!E14+'PRESTAMO '!F14)) -> 5.5600021e+09 | E14: =IF(C14>$D$8,"",$D$6*G13) -> 1.8623481e+09 | F14: =IF(C14>$D$8,"",IF(CONTROL!$G$29=1,D14-E14,'PRESTAMO '!$D$2/'PRESTAMO '!$D$8)) -> 3.6976539e+09 | G14: =IF(C14>$D$8,"",G13-F14) -> 1.8212324e+10 | H14: =+IF(D14="",0,(E14*0.21)/1.21) -> 3.2321745e+08
C15: =IF(OR(C14=$D$8,C14=""),"",IF(ISNUMBER(C14),C14+1,1)) -> 3 | D15: =IF(C15>$D$8,"",IF(CONTROL!$G$29=1,PMT($D$6,$D$8,$D$2)*-1,'PRESTAMO '!E15+'PRESTAMO '!F15)) -> 5.5600021e+09 | E15: =IF(C15>$D$8,"",$D$6*G14) -> 1.5480476e+09 | F15: =IF(C15>$D$8,"",IF(CONTROL!$G$29=1,D15-E15,'PRESTAMO '!$D$2/'PRESTAMO '!$D$8)) -> 4.0119545e+09 | G15: =IF(C15>$D$8,"",G14-F15) -> 1.420037e+10 | H15: =+IF(D15="",0,(E15*0.21)/1.21) -> 2.6866941e+08
C16: =IF(OR(C15=$D$8,C15=""),"",IF(ISNUMBER(C15),C15+1,1)) -> 4 | D16: =IF(C16>$D$8,"",IF(CONTROL!$G$29=1,PMT($D$6,$D$8,$D$2)*-1,'PRESTAMO '!E16+'PRESTAMO '!F16)) -> 5.5600021e+09 | E16: =IF(C16>$D$8,"",$D$6*G15) -> 1.2070314e+09 | F16: =IF(C16>$D$8,"",IF(CONTROL!$G$29=1,D16-E16,'PRESTAMO '!$D$2/'PRESTAMO '!$D$8)) -> 4.3529707e+09 | G16: =IF(C16>$D$8,"",G15-F16) -> 9.8473991e+09 | H16: =+IF(D16="",0,(E16*0.21)/1.21) -> 2.0948479e+08
C17: =IF(OR(C16=$D$8,C16=""),"",IF(ISNUMBER(C16),C16+1,1)) -> 5 | D17: =IF(C17>$D$8,"",IF(CONTROL!$G$29=1,PMT($D$6,$D$8,$D$2)*-1,'PRESTAMO '!E17+'PRESTAMO '!F17)) -> 5.5600021e+09 | E17: =IF(C17>$D$8,"",$D$6*G16) -> 8.3702892e+08 | F17: =IF(C17>$D$8,"",IF(CONTROL!$G$29=1,D17-E17,'PRESTAMO '!$D$2/'PRESTAMO '!$D$8)) -> 4.7229732e+09 | G17: =IF(C17>$D$8,"",G16-F17) -> 5.1244259e+09 | H17: =+IF(D17="",0,(E17*0.21)/1.21) -> 1.4526948e+08
C18: =IF(OR(C17=$D$8,C17=""),"",IF(ISNUMBER(C17),C17+1,1)) -> 6 | D18: =IF(C18>$D$8,"",IF(CONTROL!$G$29=1,PMT($D$6,$D$8,$D$2)*-1,'PRESTAMO '!E18+'PRESTAMO '!F18)) -> 5.5600021e+09 | E18: =IF(C18>$D$8,"",$D$6*G17) -> 4.355762e+08 | F18: =IF(C18>$D$8,"",IF(CONTROL!$G$29=1,D18-E18,'PRESTAMO '!$D$2/'PRESTAMO '!$D$8)) -> 5.1244259e+09 | G18: =IF(C18>$D$8,"",G17-F18) -> -5.7220459e-06 | H18: =+IF(D18="",0,(E18*0.21)/1.21) -> 75595870
C19: =IF(OR(C18=$D$8,C18=""),"",IF(ISNUMBER(C18),C18+1,1)) | D19: =IF(C19>$D$8,"",IF(CONTROL!$G$29=1,PMT($D$6,$D$8,$D$2)*-1,'PRESTAMO '!E19+'PRESTAMO '!F19)) | E19: =IF(C19>$D$8,"",$D$6*G18) | F19: =IF(C19>$D$8,"",IF(CONTROL!$G$29=1,D19-E19,'PRESTAMO '!$D$2/'PRESTAMO '!$D$8)) | G19: =IF(C19>$D$8,"",G18-F19) | H19: =+IF(D19="",0,(E19*0.21)/1.21) -> 0
C20: =IF(OR(C19=$D$8,C19=""),"",IF(ISNUMBER(C19),C19+1,1)) | D20: =IF(C20>$D$8,"",IF(CONTROL!$G$29=1,PMT($D$6,$D$8,$D$2)*-1,'PRESTAMO '!E20+'PRESTAMO '!F20)) | E20: =IF(C20>$D$8,"",$D$6*G19) | F20: =IF(C20>$D$8,"",IF(CONTROL!$G$29=1,D20-E20,'PRESTAMO '!$D$2/'PRESTAMO '!$D$8)) | G20: =IF(C20>$D$8,"",G19-F20) | H20: =+IF(D20="",0,(E20*0.21)/1.21) -> 0
C21: =IF(OR(C20=$D$8,C20=""),"",IF(ISNUMBER(C20),C20+1,1)) | D21: =IF(C21>$D$8,"",IF(CONTROL!$G$29=1,PMT($D$6,$D$8,$D$2)*-1,'PRESTAMO '!E21+'PRESTAMO '!F21)) | E21: =IF(C21>$D$8,"",$D$6*G20) | F21: =IF(C21>$D$8,"",IF(CONTROL!$G$29=1,D21-E21,'PRESTAMO '!$D$2/'PRESTAMO '!$D$8)) | G21: =IF(C21>$D$8,"",G20-F21) | H21: =+IF(D21="",0,(E21*0.21)/1.21) -> 0
C22: =IF(OR(C21=$D$8,C21=""),"",IF(ISNUMBER(C21),C21+1,1)) | D22: =IF(C22>$D$8,"",IF(CONTROL!$G$29=1,PMT($D$6,$D$8,$D$2)*-1,'PRESTAMO '!E22+'PRESTAMO '!F22)) | E22: =IF(C22>$D$8,"",$D$6*G21) | F22: =IF(C22>$D$8,"",IF(CONTROL!$G$29=1,D22-E22,'PRESTAMO '!$D$2/'PRESTAMO '!$D$8)) | G22: =IF(C22>$D$8,"",G21-F22) | H22: =+IF(D22="",0,(E22*0.21)/1.21) -> 0
C23: =IF(OR(C22=$D$8,C22=""),"",IF(ISNUMBER(C22),C22+1,1)) | D23: =IF(C23>$D$8,"",IF(CONTROL!$G$29=1,PMT($D$6,$D$8,$D$2)*-1,'PRESTAMO '!E23+'PRESTAMO '!F23)) | E23: =IF(C23>$D$8,"",$D$6*G22) | F23: =IF(C23>$D$8,"",IF(CONTROL!$G$29=1,D23-E23,'PRESTAMO '!$D$2/'PRESTAMO '!$D$8)) | G23: =IF(C23>$D$8,"",G22-F23) | H23: =+IF(D23="",0,(E23*0.21)/1.21) -> 0
C24: =IF(OR(C23=$D$8,C23=""),"",IF(ISNUMBER(C23),C23+1,1)) | D24: =IF(C24>$D$8,"",IF(CONTROL!$G$29=1,PMT($D$6,$D$8,$D$2)*-1,'PRESTAMO '!E24+'PRESTAMO '!F24)) | E24: =IF(C24>$D$8,"",$D$6*G23) | F24: =IF(C24>$D$8,"",IF(CONTROL!$G$29=1,D24-E24,'PRESTAMO '!$D$2/'PRESTAMO '!$D$8)) | G24: =IF(C24>$D$8,"",G23-F24) | H24: =+IF(D24="",0,(E24*0.21)/1.21) -> 0
C25: =IF(OR(C24=$D$8,C24=""),"",IF(ISNUMBER(C24),C24+1,1)) | D25: =IF(C25>$D$8,"",IF(CONTROL!$G$29=1,PMT($D$6,$D$8,$D$2)*-1,'PRESTAMO '!E25+'PRESTAMO '!F25)) | E25: =IF(C25>$D$8,"",$D$6*G24) | F25: =IF(C25>$D$8,"",IF(CONTROL!$G$29=1,D25-E25,'PRESTAMO '!$D$2/'PRESTAMO '!$D$8)) | G25: =IF(C25>$D$8,"",G24-F25) | H25: =+IF(D25="",0,(E25*0.21)/1.21) -> 0
... C32: =IF(OR(C31=$D$8,C31=""),"",IF(ISNUMBER(C31),C31+1,1)) | D32: =IF(C32>$D$8,"",IF(CONTROL!$G$29=1,PMT($D$6,$D$8,$D$2)*-1,'PRESTAMO '!E32+'PRESTAMO '!F32)) | E32: =IF(C32>$D$8,"",$D$6*G31) | F32: =IF(C32>$D$8,"",IF(CONTROL!$G$29=1,D32-E32,'PRESTAMO '!$D$2/'PRESTAMO '!$D$8)) | G32: =IF(C32>$D$8,"",G31-F32) | H32: =+IF(D32="",0,(E32*0.21)/1.21) -> 0
C33: =IF(OR(C32=$D$8,C32=""),"",IF(ISNUMBER(C32),C32+1,1)) | D33: =IF(C33>$D$8,"",PMT($D$6,$D$8,$D$2)*-1) | E33: =IF(C33>$D$8,"",$D$6*G32) | F33: =IF(C33>$D$8,"",D33-E33) | G33: =IF(C33>$D$8,"",G32-F33)
C34: =IF(OR(C33=$D$8,C33=""),"",IF(ISNUMBER(C33),C33+1,1)) | D34: =IF(C34>$D$8,"",PMT($D$6,$D$8,$D$2)*-1) | E34: =IF(C34>$D$8,"",$D$6*G33) | F34: =IF(C34>$D$8,"",D34-E34) | G34: =IF(C34>$D$8,"",G33-F34)
C35: =IF(OR(C34=$D$8,C34=""),"",IF(ISNUMBER(C34),C34+1,1)) | D35: =IF(C35>$D$8,"",PMT($D$6,$D$8,$D$2)*-1) | E35: =IF(C35>$D$8,"",$D$6*G34) | F35: =IF(C35>$D$8,"",D35-E35) | G35: =IF(C35>$D$8,"",G34-F35)
C36: =IF(OR(C35=$D$8,C35=""),"",IF(ISNUMBER(C35),C35+1,1)) | D36: =IF(C36>$D$8,"",PMT($D$6,$D$8,$D$2)*-1) | E36: =IF(C36>$D$8,"",$D$6*G35) | F36: =IF(C36>$D$8,"",D36-E36) | G36: =IF(C36>$D$8,"",G35-F36)
C37: =IF(OR(C36=$D$8,C36=""),"",IF(ISNUMBER(C36),C36+1,1)) | D37: =IF(C37>$D$8,"",PMT($D$6,$D$8,$D$2)*-1) | E37: =IF(C37>$D$8,"",$D$6*G36) | F37: =IF(C37>$D$8,"",D37-E37) | G37: =IF(C37>$D$8,"",G36-F37)
C38: =IF(OR(C37=$D$8,C37=""),"",IF(ISNUMBER(C37),C37+1,1)) | D38: =IF(C38>$D$8,"",PMT($D$6,$D$8,$D$2)*-1) | E38: =IF(C38>$D$8,"",$D$6*G37) | F38: =IF(C38>$D$8,"",D38-E38) | G38: =IF(C38>$D$8,"",G37-F38)
C39: =IF(OR(C38=$D$8,C38=""),"",IF(ISNUMBER(C38),C38+1,1)) | D39: =IF(C39>$D$8,"",PMT($D$6,$D$8,$D$2)*-1) | E39: =IF(C39>$D$8,"",$D$6*G38) | F39: =IF(C39>$D$8,"",D39-E39) | G39: =IF(C39>$D$8,"",G38-F39)
C40: =IF(OR(C39=$D$8,C39=""),"",IF(ISNUMBER(C39),C39+1,1)) | D40: =IF(C40>$D$8,"",PMT($D$6,$D$8,$D$2)*-1) | E40: =IF(C40>$D$8,"",$D$6*G39) | F40: =IF(C40>$D$8,"",D40-E40) | G40: =IF(C40>$D$8,"",G39-F40)
C41: =IF(OR(C40=$D$8,C40=""),"",IF(ISNUMBER(C40),C40+1,1)) | D41: =IF(C41>$D$8,"",PMT($D$6,$D$8,$D$2)*-1) | E41: =IF(C41>$D$8,"",$D$6*G40) | F41: =IF(C41>$D$8,"",D41-E41) | G41: =IF(C41>$D$8,"",G40-F41)
C42: =IF(OR(C41=$D$8,C41=""),"",IF(ISNUMBER(C41),C41+1,1)) | D42: =IF(C42>$D$8,"",PMT($D$6,$D$8,$D$2)*-1) | E42: =IF(C42>$D$8,"",$D$6*G41) | F42: =IF(C42>$D$8,"",D42-E42) | G42: =IF(C42>$D$8,"",G41-F42)
C43: =IF(OR(C42=$D$8,C42=""),"",IF(ISNUMBER(C42),C42+1,1)) | D43: =IF(C43>$D$8,"",PMT($D$6,$D$8,$D$2)*-1) | E43: =IF(C43>$D$8,"",$D$6*G42) | F43: =IF(C43>$D$8,"",D43-E43) | G43: =IF(C43>$D$8,"",G42-F43)
C44: =IF(OR(C43=$D$8,C43=""),"",IF(ISNUMBER(C43),C43+1,1)) | D44: =IF(C44>$D$8,"",PMT($D$6,$D$8,$D$2)*-1) | E44: =IF(C44>$D$8,"",$D$6*G43) | F44: =IF(C44>$D$8,"",D44-E44) | G44: =IF(C44>$D$8,"",G43-F44)
... C399: =IF(OR(C398=$D$8,C398=""),"",IF(ISNUMBER(C398),C398+1,1)) | D399: =IF(C399>$D$8,"",PMT($D$6,$D$8,$D$2)*-1) | E399: =IF(C399>$D$8,"",$D$6*G398) | F399: =IF(C399>$D$8,"",D399-E399) | G399: =IF(C399>$D$8,"",G398-F399)

Sheet HIPOTESIS
B3: =+CAPEX!B2 -> 1 de junio 2026 | C3: =+FLUJO!C4 -> 2027 | D3: =+FLUJO!D4 -> 2028 | E3: =+FLUJO!E4 -> 2029 | F3: =+FLUJO!F4 -> 2030 | G3: =+FLUJO!G4 -> 2031 | H3: =+FLUJO!H4 -> 2032 | I3: =+FLUJO!I4 -> 2033 | J3: =+FLUJO!J4 -> 2034 | ... V3: =+FLUJO!V4 -> 2046
B4: =+CONTROL!B2 -> TIR Nominal (con IVA) | C4: =+FLUJO!C5 -> 46388 | D4: =+FLUJO!D5 -> 46753 | E4: =+FLUJO!E5 -> 47119 | F4: =+FLUJO!F5 -> 47484 | G4: =+FLUJO!G5 -> 47849 | H4: =+FLUJO!H5 -> 48214 | I4: =+FLUJO!I5 -> 48580 | J4: =+FLUJO!J5 -> 48945 | ... V4: =+FLUJO!V5 -> 53328
B5: =+CONTROL!C2 -> 2.2128475 | C5: =+FLUJO!C6 -> 46752 | D5: =+FLUJO!D6 -> 47118 | E5: =+FLUJO!E6 -> 47483 | F5: =+FLUJO!F6 -> 47848 | G5: =+FLUJO!G6 -> 48213 | H5: =+FLUJO!H6 -> 48579 | I5: =+FLUJO!I6 -> 48944 | J5: =+FLUJO!J6 -> 49309 | ... V5: =+FLUJO!V6 -> 53692
B7: Año de Concesión | C7: =+FLUJO!C8 -> 1 | D7: =+FLUJO!D8 -> 2 | E7: =+FLUJO!E8 -> 3 | F7: =+FLUJO!F8 -> 4 | G7: =+FLUJO!G8 -> 5 | H7: =+FLUJO!H8 -> 6 | I7: =+FLUJO!I8 -> 7 | J7: =+FLUJO!J8 -> 8 | ... V7: =+FLUJO!V8 -> 20
B8: Días del Año | C8: =+FLUJO!C9 -> 365 | D8: =+FLUJO!D9 -> 366 | E8: =+FLUJO!E9 -> 365 | F8: =+FLUJO!F9 -> 365 | G8: =+FLUJO!G9 -> 365 | H8: =+FLUJO!H9 -> 366 | I8: =+FLUJO!I9 -> 365 | J8: =+FLUJO!J9 -> 365 | ... V8: =+FLUJO!V9 -> 365
B9: Días del Año (Operación) | C9: =+FLUJO!C10 -> 365 | D9: =+FLUJO!D10 -> 366 | E9: =+FLUJO!E10 -> 365 | F9: =+FLUJO!F10 -> 365 | G9: =+FLUJO!G10 -> 365 | H9: =+FLUJO!H10 -> 366 | I9: =+FLUJO!I10 -> 365 | J9: =+FLUJO!J10 -> 365 | ... V9: =+FLUJO!V10 -> 365
B10: Días del Año (Construcción) | C10: =+FLUJO!C11 -> 365 | D10: =+FLUJO!D11 -> 366 | E10: =+FLUJO!E11 -> 365 | F10: =+FLUJO!F11 -> 365 | G10: =+FLUJO!G11 -> 365 | H10: =+FLUJO!H11 -> 366 | I10: =+FLUJO!I11 -> 365 | J10: =+FLUJO!J11 -> 365 | ... V10: =+FLUJO!V11 -> 365
B11: Factor de Ingresos | C11: =+C12 -> 1 | D11: 1 | E11: 1 | F11: 1 | G11: 1 | H11: 1 | I11: 1 | J11: 1 | K11: 1 | L11: 1 | M11: 1 | N11: 1 | O11: 1 | P11: 1 | Q11: 1 | R11: 1 | S11: 1 | T11: 1 | U11: 1 | V11: 1
B12: Factor de Operación | C12: 1 | D12: 1 | E12: 1 | F12: 1 | G12: 1 | H12: =+G12 -> 1 | I12: =+H12 -> 1 | J12: =+I12 -> 1 | K12: =+J12 -> 1 | L12: =+K12 -> 1 | M12: =+L12 -> 1 | N12: =+M12 -> 1 | O12: =+N12 -> 1 | ... V12: =+U12 -> 1
B13: Factor de Construcción I | C13: 1 | D13: 1 | E13: 1 | F13: 1 | G13: 1 | H13: =+G13 -> 1 | I13: =+H13 -> 1 | J13: =+I13 -> 1 | K13: =+J13 -> 1 | L13: =+K13 -> 1 | M13: =+L13 -> 1 | N13: =+M13 -> 1 | O13: =+N13 -> 1 | ... V13: =+U13 -> 1
B14: Factor de Construcción II | C14: 1 | D14: 1 | E14: 1 | F14: 1 | G14: 1 | H14: 1 | I14: 1 | J14: 1 | K14: 1 | L14: 1 | M14: 1 | N14: 1 | O14: 1 | P14: 1 | Q14: 1 | R14: 1 | S14: 1 | T14: 1 | U14: 1 | V14: 1
B15: Factor de Construcción III | C15: 1 | D15: 1 | E15: 1 | F15: 1 | G15: 1 | H15: 1 | I15: 1 | J15: 1 | K15: 1 | L15: 1 | M15: 1 | N15: 1 | O15: 1 | P15: 1 | Q15: 1 | R15: 1 | S15: 1 | T15: 1 | U15: 1 | V15: 1
B17: INGRESOS (sin IVA)
B18: Peajes existentes | C18: 1 | D18: =+D11 -> 1 | E18: =+E11 -> 1 | F18: =+F11 -> 1 | G18: =+G11 -> 1 | H18: =+H11 -> 1 | I18: =+I11 -> 1 | J18: =+J11 -> 1 | K18: =+K11 -> 1 | ... V18: =+V11 -> 1
B19: Peajes nuevos | C19: =+C18 -> 1 | D19: 1 | E19: 1 | F19: 1 | G19: 1 | H19: 1 | I19: =+I18 -> 1 | J19: =+J18 -> 1 | K19: =+K18 -> 1 | L19: =+L18 -> 1 | M19: =+M18 -> 1 | N19: =+N18 -> 1 | O19: =+O18 -> 1 | P19: =+P18 -> 1 | ... V19: =+V18 -> 1
B20: Otros Ingresos | C20: =+C19 -> 1 | D20: 1 | E20: 1 | F20: 1 | G20: 1 | H20: 1 | I20: =+I19 -> 1 | J20: =+J19 -> 1 | K20: =+K19 -> 1 | L20: =+L19 -> 1 | M20: =+M19 -> 1 | N20: =+N19 -> 1 | O20: =+O19 -> 1 | P20: =+P19 -> 1 | ... V20: =+V19 -> 1
B21: Ingresos Deuda LP | C21: 1
B23: OPEX
B24: Conservación y Mantenimiento | C24: 1 | D24: =+D12 -> 1 | E24: =+E12 -> 1 | F24: =+F12 -> 1 | G24: =+G12 -> 1 | H24: =+H12 -> 1 | I24: =+I12 -> 1 | J24: =+J12 -> 1 | K24: =+K12 -> 1 | ... V24: =+V12 -> 1
B25: Atención al Usuario | C25: =+C24 -> 1 | D25: =+D24 -> 1 | E25: =+E24 -> 1 | F25: =+F24 -> 1 | G25: =+G24 -> 1 | H25: =+H24 -> 1 | I25: =+I24 -> 1 | J25: =+J24 -> 1 | ... V25: =+V24 -> 1
B26: Administración | C26: =+C25 -> 1 | D26: =+D25 -> 1 | E26: =+E25 -> 1 | F26: =+F25 -> 1 | G26: =+G25 -> 1 | H26: =+H25 -> 1 | I26: =+I25 -> 1 | J26: =+J25 -> 1 | ... V26: =+V25 -> 1
B27: Explotación | C27: =+C26 -> 1 | D27: =+D26 -> 1 | E27: =+E26 -> 1 | F27: =+F26 -> 1 | G27: =+G26 -> 1 | H27: =+H26 -> 1 | I27: =+I26 -> 1 | J27: =+J26 -> 1 | ... V27: =+V26 -> 1
B28: Amortización de la deuda | C28: 1 | D28: =+D27 -> 1 | E28: =+E27 -> 1 | F28: =+F27 -> 1 | G28: =+G27 -> 1 | H28: =+H27 -> 1 | I28: =+I27 -> 1 | J28: =+J27 -> 1 | K28: =+K27 -> 1 | ... V28: =+V27 -> 1
B30: CAPEX
B31: Obras de Puesta en Valor | C31: 1 | D31: =+D13 -> 1 | E31: =+E13 -> 1 | F31: =+F13 -> 1 | G31: =+G13 -> 1 | H31: =+H13 -> 1 | I31: =+I13 -> 1 | J31: =+J13 -> 1 | K31: =+K13 -> 1 | ... V31: =+V13 -> 1
B32: Obras Obligatorias | C32: 1 | D32: =+D14 -> 1 | E32: =+E14 -> 1 | F32: =+F14 -> 1 | G32: =+G14 -> 1 | H32: =+H14 -> 1 | I32: =+I14 -> 1 | J32: =+J14 -> 1 | K32: =+K14 -> 1 | ... V32: =+V14 -> 1
B33: Gastos Repavimentación | C33: 1 | D33: =+D15 -> 1 | E33: =+E15 -> 1 | F33: =+F15 -> 1 | G33: =+G15 -> 1 | H33: =+H15 -> 1 | I33: =+I15 -> 1 | J33: =+J15 -> 1 | K33: =+K15 -> 1 | ... V33: =+V15 -> 1

Sheet IMPUESTOS
B2: =+FLUJO!B4 -> 1 de junio 2026 | D2: =+FLUJO!C4 -> 2027 | E2: =+FLUJO!D4 -> 2028 | F2: =+FLUJO!E4 -> 2029 | G2: =+FLUJO!F4 -> 2030 | H2: =+FLUJO!G4 -> 2031 | I2: =+FLUJO!H4 -> 2032 | J2: =+FLUJO!I4 -> 2033 | K2: =+FLUJO!J4 -> 2034 | ... W2: =+FLUJO!V4 -> 2046
B3: =+CONTROL!B2 -> TIR Nominal (con IVA) | D3: =+FLUJO!C5 -> 46388 | E3: =+FLUJO!D5 -> 46753 | F3: =+FLUJO!E5 -> 47119 | G3: =+FLUJO!F5 -> 47484 | H3: =+FLUJO!G5 -> 47849 | I3: =+FLUJO!H5 -> 48214 | J3: =+FLUJO!I5 -> 48580 | K3: =+FLUJO!J5 -> 48945 | ... W3: =+FLUJO!V5 -> 53328
B4: =+FLUJO!B6 -> 2.2128475 | D4: =+FLUJO!C6 -> 46752 | E4: =+FLUJO!D6 -> 47118 | F4: =+FLUJO!E6 -> 47483 | G4: =+FLUJO!F6 -> 47848 | H4: =+FLUJO!G6 -> 48213 | I4: =+FLUJO!H6 -> 48579 | J4: =+FLUJO!I6 -> 48944 | K4: =+FLUJO!J6 -> 49309 | ... W4: =+FLUJO!V6 -> 53692
B6: Año de Concesión | D6: 1 | E6: 2 | F6: 3 | G6: 4 | H6: 5 | I6: 6 | J6: 7 | K6: 8 | L6: 9 | M6: 10 | N6: 11 | O6: 12 | P6: 13 | Q6: 14 | R6: 15 | S6: 16 | T6: 17 | U6: 18 | V6: 19 | W6: 20
B7: Días del Año | D7: =+D4-D3+1 -> 365 | E7: =+E4-E3+1 -> 366 | F7: =+F4-F3+1 -> 365 | G7: =+G4-G3+1 -> 365 | H7: =+H4-H3+1 -> 365 | I7: =+I4-I3+1 -> 366 | J7: =+J4-J3+1 -> 365 | K7: =+K4-K3+1 -> 365 | ... W7: =+W4-W3+1 -> 365
B8: Días del Año (Operación) | D8: =+-D3+D4+1 -> 365 | E8: =+E7 -> 366 | F8: =+F7 -> 365 | G8: =+G7 -> 365 | H8: =+H7 -> 365 | I8: =+I7 -> 366 | J8: =+J7 -> 365 | K8: =+K7 -> 365 | L8: =+L7 -> 365 | ... W8: =+W7 -> 365
B9: Días del Año (Construcción) | D9: =+D8 -> 365 | E9: =+E8 -> 366 | F9: =+F8 -> 365 | G9: =+G8 -> 365 | H9: =+H8 -> 365 | I9: =+I8 -> 366 | J9: =+J8 -> 365 | K9: =+K8 -> 365 | ... W9: =+W8 -> 365
B10: Factor de Ingresos | D10: =+HIPOTESIS!C11 -> 1 | E10: =+HIPOTESIS!D11 -> 1 | F10: =+HIPOTESIS!E11 -> 1 | G10: =+HIPOTESIS!F11 -> 1 | H10: =+HIPOTESIS!G11 -> 1 | I10: =+HIPOTESIS!H11 -> 1 | J10: =+HIPOTESIS!I11 -> 1 | K10: =+HIPOTESIS!J11 -> 1 | ... W10: =+HIPOTESIS!V11 -> 1
B11: Factor de Operación | D11: =+HIPOTESIS!C12 -> 1 | E11: =+HIPOTESIS!D12 -> 1 | F11: =+HIPOTESIS!E12 -> 1 | G11: =+HIPOTESIS!F12 -> 1 | H11: =+HIPOTESIS!G12 -> 1 | I11: =+HIPOTESIS!H12 -> 1 | J11: =+HIPOTESIS!I12 -> 1 | K11: =+HIPOTESIS!J12 -> 1 | ... W11: =+HIPOTESIS!V12 -> 1
B12: Factor de Construcción | D12: =+HIPOTESIS!C13 -> 1 | E12: =+HIPOTESIS!D13 -> 1 | F12: =+HIPOTESIS!E13 -> 1 | G12: =+HIPOTESIS!F13 -> 1 | H12: =+HIPOTESIS!G13 -> 1 | I12: =+HIPOTESIS!H13 -> 1 | J12: =+HIPOTESIS!I13 -> 1 | K12: =+HIPOTESIS!J13 -> 1 | ... W12: =+HIPOTESIS!V13 -> 1
X13: TOTAL
Z15: Ingresos Brutos | AA15: =+CONTROL!C43 -> 0.025
B16: INGRESOS BRUTOS | D16: =+(SUM(FLUJO!C73:C75)/1.21)*IMPUESTOS!$AA$15 -> 0 | E16: =+(SUM(FLUJO!D73:D75)/1.21)*IMPUESTOS!$AA$15 -> 7.2425514e+08 | F16: =+(SUM(FLUJO!E73:E75)/1.21)*IMPUESTOS!$AA$15 -> 7.4598279e+08 | G16: =+(SUM(FLUJO!F73:F75)/1.21)*IMPUESTOS!$AA$15 -> 7.6836228e+08 | H16: =+(SUM(FLUJO!G73:G75)/1.21)*IMPUESTOS!$AA$15 -> 7.9141315e+08 | I16: =+(SUM(FLUJO!H73:H75)/1.21)*IMPUESTOS!$AA$15 -> 8.1515554e+08 | J16: =+(SUM(FLUJO!I73:I75)/1.21)*IMPUESTOS!$AA$15 -> 8.3961021e+08 | K16: =+(SUM(FLUJO!J73:J75)/1.21)*IMPUESTOS!$AA$15 -> 8.6479851e+08 | ... W16: =+(SUM(FLUJO!V73:V75)/1.21)*IMPUESTOS!$AA$15 -> 1.2329959e+09 | X16: =SUM(D16:W16) -> 1.8191021e+10 | Z16: Impuesto a las Ganancias | AA16: =+CONTROL!C44 -> 0.35
Z17: Impuesto al Débito y Crédito Bancario | AA17: =+CONTROL!C45 -> 0.012
B18: IVA | D18: =+D41 -> 0 | E18: =+E41 -> 2.535362e+08 | F18: =+F41 -> 2.5988413e+09 | G18: =+G41 -> 1.1691756e+09 | H18: =+H41 -> 2.9681748e+09 | I18: =+I41 -> 2.3970324e+09 | J18: =+J41 -> 1.5750136e+09 | K18: =+K41 -> 1.7865953e+09 | ... W18: =+W41 -> 7.9617674e+09 | X18: =SUM(D18:W18) -> 8.8136841e+10 | Z18: Impuesto al Crédito | AA18: 0.0006
Z19: IVA | AA19: =+CONTROL!C46 -> 0.21
B20: Impuesto de Sellos | D20: =+FLUJO!W97/(1+IMPUESTOS!AA19)*IMPUESTOS!AA26/5 -> 4.6283345e+08 | E20: =+D20 -> 4.6283345e+08 | F20: =+E20 -> 4.6283345e+08 | G20: =+F20 -> 4.6283345e+08 | H20: =+G20 -> 4.6283345e+08 | X20: =SUM(D20:W20) -> 2.3141673e+09 | Z20: IVA OPEX | AA20: =+CONTROL!C47 -> 0.11
Z21: IVA CAPEX | AA21: =+CONTROL!C52 -> 0.21
B22: Tasas Municipales | D22: =+((SUM(FLUJO!C73:C75))/(1+IMPUESTOS!$AA$19))*IMPUESTOS!$AA$27 -> 0 | E22: =+((FLUJO!D77)/(1+IMPUESTOS!$AA$19))*IMPUESTOS!$AA$27 -> 1.4485103e+08 | F22: =+((FLUJO!E77)/(1+IMPUESTOS!$AA$19))*IMPUESTOS!$AA$27 -> 1.4919656e+08 | G22: =+((FLUJO!F77)/(1+IMPUESTOS!$AA$19))*IMPUESTOS!$AA$27 -> 1.5367246e+08 | H22: =+((FLUJO!G77)/(1+IMPUESTOS!$AA$19))*IMPUESTOS!$AA$27 -> 1.5828263e+08 | I22: =+((FLUJO!H77)/(1+IMPUESTOS!$AA$19))*IMPUESTOS!$AA$27 -> 1.6303111e+08 | J22: =+((FLUJO!I77)/(1+IMPUESTOS!$AA$19))*IMPUESTOS!$AA$27 -> 1.6792204e+08 | K22: =+((FLUJO!J77)/(1+IMPUESTOS!$AA$19))*IMPUESTOS!$AA$27 -> 1.729597e+08 | L22: =+((FLUJO!K77)/(1+IMPUESTOS!$AA$19))*IMPUESTOS!$AA$27 -> 1.7814849e+08 | ... W22: =+((FLUJO!V77)/(1+IMPUESTOS!$AA$19))*IMPUESTOS!$AA$27 -> 2.4659918e+08 | X22: =SUM(D22:W22) -> 3.6382042e+09 | Z22: IVA (Conservación y Mantenimiento) | AA22: =+CONTROL!C48 -> 0.15
Z23: IVA (Atención al Usuario) | AA23: =+CONTROL!C49 -> 0.08
B24: Impuesto D/C | D24: =+FLUJO!C77*IMPUESTOS!$AA$17 -> 2.8001424e+08 | E24: =+FLUJO!D77*IMPUESTOS!$AA$17 -> 4.2064739e+08 | F24: =+FLUJO!E77*IMPUESTOS!$AA$17 -> 4.3326681e+08 | G24: =+FLUJO!F77*IMPUESTOS!$AA$17 -> 4.4626481e+08 | H24: =+FLUJO!G77*IMPUESTOS!$AA$17 -> 4.5965276e+08 | I24: =+FLUJO!H77*IMPUESTOS!$AA$17 -> 4.7344234e+08 | J24: =+FLUJO!I77*IMPUESTOS!$AA$17 -> 4.8764561e+08 | K24: =+FLUJO!J77*IMPUESTOS!$AA$17 -> 5.0227498e+08 | ... W24: =+FLUJO!V77*IMPUESTOS!$AA$17 -> 7.1612402e+08 | X24: =SUM(D24:W24) -> 1.0845359e+10 | Z24: IVA (Administración) | AA24: =+CONTROL!C50 -> 0.057
Z25: IVA (Explotación) | AA25: =+CONTROL!C51 -> 0.18
B26: GANANCIAS | D26: =+D66 -> 0 | E26: =+E66 -> 4.0437148e+09 | F26: =+F66 -> 5.7892452e+09 | G26: =+G66 -> 4.4714244e+09 | H26: =+H66 -> 4.3989546e+09 | I26: =+I66 -> 4.4133335e+09 | J26: =+J66 -> 4.514023e+09 | K26: =+K66 -> 4.6082432e+09 | ... W26: =+W66 -> 6.8971179e+09 | X26: =SUM(D26:W26) -> 1.1073221e+11 | Z26: Impuesto de Sellos | AA26: =+CONTROL!C53 -> 0.012
Z27: Tasas Municipales | AA27: =+CONTROL!C54 -> 0.005
B28: TOTAL IMPUESTOS | D28: =+SUM(D16:D26) -> 7.4284769e+08 | E28: =+SUM(E16:E26) -> 6.049838e+09 | F28: =+SUM(F16:F26) -> 1.0179366e+10 | G28: =+SUM(G16:G26) -> 7.471733e+09 | H28: =+SUM(H16:H26) -> 9.2393114e+09 | I28: =+SUM(I16:I26) -> 8.2619949e+09 | J28: =+SUM(J16:J26) -> 7.5842145e+09 | K28: =+SUM(K16:K26) -> 7.9348717e+09 | ... W28: =+SUM(W16:W26) -> 1.7054604e+10 | X28: =SUM(D28:W28) -> 2.338578e+11 | Z28: CPI | AA28: 0
Z29: Porcentaje de la Inversión que se Amortiza | AA29: =+CONTROL!C55 -> 1
B30: BALANCE IVA | Z30: Porcentaje deducción de Intereses en IIGG | AA30: =+CONTROL!C56 -> 0.3
B33: IVA CREDITO | D33: =(FLUJO!C80*$AA$22)/(1+$AA$22)+(FLUJO!C81*$AA$23)/(1+$AA$23)+(FLUJO!C82*$AA$24)/(1+$AA$24)+(FLUJO!C83*$AA$25)/(1+$AA$25)+(SUM(FLUJO!C97)*IMPUESTOS!$AA$21)/(1+IMPUESTOS!$AA$21)+(FLUJO!C99*$AA$19)/(1+$AA$19) -> 4.0813087e+09 | E33: =(FLUJO!D80*$AA$22)/(1+$AA$22)+(FLUJO!D81*$AA$23)/(1+$AA$23)+(FLUJO!D82*$AA$24)/(1+$AA$24)+(FLUJO!D83*$AA$25)/(1+$AA$25)+(SUM(FLUJO!D97)*IMPUESTOS!$AA$21)/(1+IMPUESTOS!$AA$21)+(FLUJO!D99*$AA$19)/(1+$AA$19) -> 1.7488983e+09 | F33: =(FLUJO!E80*$AA$22)/(1+$AA$22)+(FLUJO!E81*$AA$23)/(1+$AA$23)+(FLUJO!E82*$AA$24)/(1+$AA$24)+(FLUJO!E83*$AA$25)/(1+$AA$25)+(SUM(FLUJO!E97)*IMPUESTOS!$AA$21)/(1+IMPUESTOS!$AA$21)+(FLUJO!E99*$AA$19)/(1+$AA$19) -> 3.6674142e+09 | G33: =(FLUJO!F80*$AA$22)/(1+$AA$22)+(FLUJO!F81*$AA$23)/(1+$AA$23)+(FLUJO!F82*$AA$24)/(1+$AA$24)+(FLUJO!F83*$AA$25)/(1+$AA$25)+(SUM(FLUJO!F97)*IMPUESTOS!$AA$21)/(1+IMPUESTOS!$AA$21)+(FLUJO!F99*$AA$19)/(1+$AA$19) -> 5.2850675e+09 | H33: =(FLUJO!G80*$AA$22)/(1+$AA$22)+(FLUJO!G81*$AA$23)/(1+$AA$23)+(FLUJO!G82*$AA$24)/(1+$AA$24)+(FLUJO!G83*$AA$25)/(1+$AA$25)+(SUM(FLUJO!G97)*IMPUESTOS!$AA$21)/(1+IMPUESTOS!$AA$21)+(FLUJO!G99*$AA$19)/(1+$AA$19) -> 3.6796956e+09 | I33: =(FLUJO!H80*$AA$22)/(1+$AA$22)+(FLUJO!H81*$AA$23)/(1+$AA$23)+(FLUJO!H82*$AA$24)/(1+$AA$24)+(FLUJO!H83*$AA$25)/(1+$AA$25)+(SUM(FLUJO!H97)*IMPUESTOS!$AA$21)/(1+IMPUESTOS!$AA$21)+(FLUJO!H99*$AA$19)/(1+$AA$19) -> 4.4502742e+09 | J33: =(FLUJO!I80*$AA$22)/(1+$AA$22)+(FLUJO!I81*$AA$23)/(1+$AA$23)+(FLUJO!I82*$AA$24)/(1+$AA$24)+(FLUJO!I83*$AA$25)/(1+$AA$25)+(SUM(FLUJO!I97)*IMPUESTOS!$AA$21)/(1+IMPUESTOS!$AA$21)+(FLUJO!I99*$AA$19)/(1+$AA$19) -> 5.4777122e+09 | K33: =(FLUJO!J80*$AA$22)/(1+$AA$22)+(FLUJO!J81*$AA$23)/(1+$AA$23)+(FLUJO!J82*$AA$24)/(1+$AA$24)+(FLUJO!J83*$AA$25)/(1+$AA$25)+(SUM(FLUJO!J97)*IMPUESTOS!$AA$21)/(1+IMPUESTOS!$AA$21)+(FLUJO!J99*$AA$19)/(1+$AA$19) -> 5.4777122e+09 | ... W33: =(FLUJO!V80*$AA$22)/(1+$AA$22)+(FLUJO!V81*$AA$23)/(1+$AA$23)+(FLUJO!V82*$AA$24)/(1+$AA$24)+(FLUJO!V83*$AA$25)/(1+$AA$25)+(SUM(FLUJO!V97)*IMPUESTOS!$AA$21)/(1+IMPUESTOS!$AA$21)+(FLUJO!V99*$AA$19)/(1+$AA$19) -> 2.3953981e+09 | X33: =SUM(D33:W33) -> 6.4667736e+10
B35: IVA DEBITO | D35: =+(SUM(FLUJO!C73:C75)*IMPUESTOS!$AA$19)/(1+IMPUESTOS!$AA$19) -> 0 | E35: =+(SUM(FLUJO!D73:D75)*IMPUESTOS!$AA$19)/(1+IMPUESTOS!$AA$19) -> 6.0837432e+09 | F35: =+(SUM(FLUJO!E73:E75)*IMPUESTOS!$AA$19)/(1+IMPUESTOS!$AA$19) -> 6.2662555e+09 | G35: =+(SUM(FLUJO!F73:F75)*IMPUESTOS!$AA$19)/(1+IMPUESTOS!$AA$19) -> 6.4542431e+09 | H35: =+(SUM(FLUJO!G73:G75)*IMPUESTOS!$AA$19)/(1+IMPUESTOS!$AA$19) -> 6.6478704e+09 | I35: =+(SUM(FLUJO!H73:H75)*IMPUESTOS!$AA$19)/(1+IMPUESTOS!$AA$19) -> 6.8473065e+09 | J35: =+(SUM(FLUJO!I73:I75)*IMPUESTOS!$AA$19)/(1+IMPUESTOS!$AA$19) -> 7.0527257e+09 | K35: =+(SUM(FLUJO!J73:J75)*IMPUESTOS!$AA$19)/(1+IMPUESTOS!$AA$19) -> 7.2643075e+09 | ... W35: =+(SUM(FLUJO!V73:V75)*IMPUESTOS!$AA$19)/(1+IMPUESTOS!$AA$19) -> 1.0357166e+10 | X35: =SUM(D35:W35) -> 1.5280458e+11
B37: POSICION IVA | D37: =+D35-D33 -> -4.0813087e+09 | E37: =+E35-E33 -> 4.3348449e+09 | F37: =+F35-F33 -> 2.5988413e+09 | G37: =+G35-G33 -> 1.1691756e+09 | H37: =+H35-H33 -> 2.9681748e+09 | I37: =+I35-I33 -> 2.3970324e+09 | J37: =+J35-J33 -> 1.5750136e+09 | K37: =+K35-K33 -> 1.7865953e+09 | ... W37: =+W35-W33 -> 7.9617674e+09 | X37: =SUM(D37:W37) -> 8.8136841e+10
B39: IVA ACUMULADO | D39: =IF(((D37+C39)<0),(D37+C39),D37) -> -4.0813087e+09 | E39: =IF(((E37+D39)<0),(E37+D39),E37) -> 4.3348449e+09 | F39: =IF(((F37+E39)<0),(F37+E39),F37) -> 2.5988413e+09 | G39: =IF(((G37+F39)<0),(G37+F39),G37) -> 1.1691756e+09 | H39: =IF(((H37+G39)<0),(H37+G39),H37) -> 2.9681748e+09 | I39: =IF(((I37+H39)<0),(I37+H39),I37) -> 2.3970324e+09 | J39: =IF(((J37+I39)<0),(J37+I39),J37) -> 1.5750136e+09 | K39: =IF(((K37+J39)<0),(K37+J39),K37) -> 1.7865953e+09 | ... W39: =IF(((W37+V39)<0),(W37+V39),W37) -> 7.9617674e+09 | X39: =SUM(D39:W39) -> 8.8136841e+10
B41: PAGO IVA | D41: =IF(D39<0,0,IF((AND((C39<=0),(D39<0))),0,(IF(C39<0,D39+C39,D39)))) -> 0 | E41: =IF(E39<0,0,IF((AND((D39<=0),(E39<0))),0,(IF(D39<0,E39+D39,E39)))) -> 2.535362e+08 | F41: =IF(F39<0,0,IF((AND((E39<=0),(F39<0))),0,(IF(E39<0,F39+E39,F39)))) -> 2.5988413e+09 | G41: =IF(G39<0,0,IF((AND((F39<=0),(G39<0))),0,(IF(F39<0,G39+F39,G39)))) -> 1.1691756e+09 | H41: =IF(H39<0,0,IF((AND((G39<=0),(H39<0))),0,(IF(G39<0,H39+G39,H39)))) -> 2.9681748e+09 | I41: =IF(I39<0,0,IF((AND((H39<=0),(I39<0))),0,(IF(H39<0,I39+H39,I39)))) -> 2.3970324e+09 | J41: =IF(J39<0,0,IF((AND((I39<=0),(J39<0))),0,(IF(I39<0,J39+I39,J39)))) -> 1.5750136e+09 | K41: =IF(K39<0,0,IF((AND((J39<=0),(K39<0))),0,(IF(J39<0,K39+J39,K39)))) -> 1.7865953e+09 | ... W41: =IF(W39<0,0,IF((AND((V39<=0),(W39<0))),0,(IF(V39<0,W39+V39,W39)))) -> 7.9617674e+09 | X41: =SUM(D41:W41) -> 8.8136841e+10
B43: IMPUESTO A LAS GANANCIAS
B46: INGRESOS | D46: =+FLUJO!C72/(1+IMPUESTOS!$AA$19) -> 0 | E46: =+FLUJO!D77/(1+IMPUESTOS!$AA$19) -> 2.8970206e+10 | F46: =+FLUJO!E77/(1+IMPUESTOS!$AA$19) -> 2.9839312e+10 | G46: =+FLUJO!F77/(1+IMPUESTOS!$AA$19) -> 3.0734491e+10 | H46: =+FLUJO!G77/(1+IMPUESTOS!$AA$19) -> 3.1656526e+10 | I46: =+FLUJO!H77/(1+IMPUESTOS!$AA$19) -> 3.2606222e+10 | J46: =+FLUJO!I77/(1+IMPUESTOS!$AA$19) -> 3.3584408e+10 | K46: =+FLUJO!J77/(1+IMPUESTOS!$AA$19) -> 3.4591941e+10 | L46: =+FLUJO!K77/(1+IMPUESTOS!$AA$19) -> 3.5629699e+10 | ... W46: =+FLUJO!V77/(1+IMPUESTOS!$AA$19) -> 4.9319836e+10 | X46: =SUM(D46:W46) -> 7.2764084e+11
B48: AMORTIZACION | D48: =IF(CONTROL!$L$16=2,AMORTIZACIONES!D48,IF(CONTROL!$L$16=1,AMORTIZACIONES!D98,AMORTIZACIONES!D148)) -> 8.1704256e+08 | E48: =IF(CONTROL!$L$16=2,AMORTIZACIONES!E48,IF(CONTROL!$L$16=1,AMORTIZACIONES!E98,AMORTIZACIONES!E148)) -> 1.8638696e+09 | F48: =IF(CONTROL!$L$16=2,AMORTIZACIONES!F48,IF(CONTROL!$L$16=1,AMORTIZACIONES!F98,AMORTIZACIONES!F148)) -> 3.3693744e+09 | G48: =IF(CONTROL!$L$16=2,AMORTIZACIONES!G48,IF(CONTROL!$L$16=1,AMORTIZACIONES!G98,AMORTIZACIONES!G148)) -> 5.2256326e+09 | H48: =IF(CONTROL!$L$16=2,AMORTIZACIONES!H48,IF(CONTROL!$L$16=1,AMORTIZACIONES!H98,AMORTIZACIONES!H148)) -> 6.6546911e+09 | I48: =IF(CONTROL!$L$16=2,AMORTIZACIONES!I48,IF(CONTROL!$L$16=1,AMORTIZACIONES!I98,AMORTIZACIONES!I148)) -> 8.3538597e+09 | J48: =IF(CONTROL!$L$16=2,AMORTIZACIONES!J48,IF(CONTROL!$L$16=1,AMORTIZACIONES!J98,AMORTIZACIONES!J148)) -> 9.4022659e+09 | K48: =IF(CONTROL!$L$16=2,AMORTIZACIONES!K48,IF(CONTROL!$L$16=1,AMORTIZACIONES!K98,AMORTIZACIONES!K148)) -> 1.0531319e+10 | ... W48: =IF(CONTROL!$L$16=2,AMORTIZACIONES!W48,IF(CONTROL!$L$16=1,AMORTIZACIONES!W98,AMORTIZACIONES!W148)) -> 1.8063886e+10 | X48: =SUM(D48:W48) -> 1.9284727e+11
B50: GASTOS | D50: =SUM(FLUJO!C80:C83)-((FLUJO!C80*$AA$22)/(1+$AA$22)+(FLUJO!C81*$AA$23)/(1+$AA$23)+(FLUJO!C82*$AA$24)/(1+$AA$24)+(FLUJO!C83*$AA$25)/(1+$AA$25))+FLUJO!C41/(1+$AA$19) -> 5.044181e+09 | E50: =SUM(FLUJO!D80:D83)-((FLUJO!D80*$AA$22)/(1+$AA$22)+(FLUJO!D81*$AA$23)/(1+$AA$23)+(FLUJO!D82*$AA$24)/(1+$AA$24)+(FLUJO!D83*$AA$25)/(1+$AA$25))+FLUJO!D41/(1+$AA$19) -> 5.044181e+09 | F50: =SUM(FLUJO!E80:E83)-((FLUJO!E80*$AA$22)/(1+$AA$22)+(FLUJO!E81*$AA$23)/(1+$AA$23)+(FLUJO!E82*$AA$24)/(1+$AA$24)+(FLUJO!E83*$AA$25)/(1+$AA$25))+FLUJO!E41/(1+$AA$19) -> 6.2756092e+09 | G50: =SUM(FLUJO!F80:F83)-((FLUJO!F80*$AA$22)/(1+$AA$22)+(FLUJO!F81*$AA$23)/(1+$AA$23)+(FLUJO!F82*$AA$24)/(1+$AA$24)+(FLUJO!F83*$AA$25)/(1+$AA$25))+FLUJO!F41/(1+$AA$19) -> 9.3541797e+09 | H50: =SUM(FLUJO!G80:G83)-((FLUJO!G80*$AA$22)/(1+$AA$22)+(FLUJO!G81*$AA$23)/(1+$AA$23)+(FLUJO!G82*$AA$24)/(1+$AA$24)+(FLUJO!G83*$AA$25)/(1+$AA$25))+FLUJO!G41/(1+$AA$19) -> 9.3541797e+09 | I50: =SUM(FLUJO!H80:H83)-((FLUJO!H80*$AA$22)/(1+$AA$22)+(FLUJO!H81*$AA$23)/(1+$AA$23)+(FLUJO!H82*$AA$24)/(1+$AA$24)+(FLUJO!H83*$AA$25)/(1+$AA$25))+FLUJO!H41/(1+$AA$19) -> 9.3541797e+09 | J50: =SUM(FLUJO!I80:I83)-((FLUJO!I80*$AA$22)/(1+$AA$22)+(FLUJO!I81*$AA$23)/(1+$AA$23)+(FLUJO!I82*$AA$24)/(1+$AA$24)+(FLUJO!I83*$AA$25)/(1+$AA$25))+FLUJO!I41/(1+$AA$19) -> 9.3541797e+09 | K50: =SUM(FLUJO!J80:J83)-((FLUJO!J80*$AA$22)/(1+$AA$22)+(FLUJO!J81*$AA$23)/(1+$AA$23)+(FLUJO!J82*$AA$24)/(1+$AA$24)+(FLUJO!J83*$AA$25)/(1+$AA$25))+FLUJO!J41/(1+$AA$19) -> 9.3541797e+09 | ... W50: =SUM(FLUJO!V80:V83)-((FLUJO!V80*$AA$22)/(1+$AA$22)+(FLUJO!V81*$AA$23)/(1+$AA$23)+(FLUJO!V82*$AA$24)/(1+$AA$24)+(FLUJO!V83*$AA$25)/(1+$AA$25))+FLUJO!V41/(1+$AA$19) -> 9.3541797e+09 | X50: =SUM(D50:W50) -> 1.7538503e+11
X52: =SUM(D52:W52) -> 0
B54: IMPUESTOS | D54: =+D16+D20+D22+D24 -> 7.4284769e+08 | E54: =+E16+E20+E22+E24 -> 1.752587e+09 | F54: =+F16+F20+F22+F24 -> 1.7912796e+09 | G54: =+G16+G20+G22+G24 -> 1.831133e+09 | H54: =+H16+H20+H22+H24 -> 1.872182e+09 | I54: =+I16+I20+I22+I24 -> 1.451629e+09 | J54: =+J16+J20+J22+J24 -> 1.4951779e+09 | K54: =+K16+K20+K22+K24 -> 1.5400332e+09 | ... W54: =+W16+W20+W22+W24 -> 2.1957191e+09 | X54: =SUM(D54:W54) -> 3.4988752e+10
B56: BASE IMPONIBLE antes de Intereses y Amortizaciones | D56: =+D46-D50-D52-D54 -> -5.7870286e+09 | E56: =+E46-E50-E52-E54 -> 2.2173438e+10 | F56: =+F46-F50-F52-F54 -> 2.1772423e+10 | G56: =+G46-G50-G52-G54 -> 1.9549178e+10 | H56: =+H46-H50-H52-H54 -> 2.0430164e+10 | I56: =+I46-I50-I52-I54 -> 2.1800413e+10 | J56: =+J46-J50-J52-J54 -> 2.2735051e+10 | K56: =+K46-K50-K52-K54 -> 2.3697728e+10 | ... W56: =+W46-W50-W52-W54 -> 3.7769937e+10 | X56: =SUM(D56:W56) -> 5.1726707e+11
B58: Calculo Intereses Deducibles Prestamo I | D58: =IF(D56>0,D56*$AA$30,0) -> 0 | E58: =IF(E56>0,E56*$AA$30,0) -> 6.6520313e+09 | F58: =IF(F56>0,F56*$AA$30,0) -> 6.5317269e+09 | G58: =IF(G56>0,G56*$AA$30,0) -> 5.8647535e+09 | H58: =IF(H56>0,H56*$AA$30,0) -> 6.1290493e+09 | I58: =IF(I56>0,I56*$AA$30,0) -> 6.5401239e+09 | J58: =IF(J56>0,J56*$AA$30,0) -> 6.8205152e+09 | K58: =IF(K56>0,K56*$AA$30,0) -> 7.1093183e+09 | ... W58: =IF(W56>0,W56*$AA$30,0) -> 1.1330981e+10 | X58: =SUM(D58:W58) -> 1.5691623e+11
B60: Calculo Intereses Deducibles Prestamo II | D60: 0 | E60: =+IF(D6>'PRESTAMO '!$D$8,0,IF(E58>'PRESTAMO '!$E$13,'PRESTAMO '!$E$13,IMPUESTOS!E58)) -> 2.1520261e+09 | F60: =+IF(E6>'PRESTAMO '!D8,0,IF(F58>'PRESTAMO '!$E$14,'PRESTAMO '!$E$14,IMPUESTOS!F58)) -> 1.8623481e+09 | G60: =+IF(F6>'PRESTAMO '!D8,0,IF(G58>'PRESTAMO '!$E$15,'PRESTAMO '!$E$15,IMPUESTOS!G58)) -> 1.5480476e+09 | H60: =IF(G6>'PRESTAMO '!D8,0,IF(H58>'PRESTAMO '!$E$16,'PRESTAMO '!$E$16,IMPUESTOS!H58)) -> 1.2070314e+09 | I60: =IF(H6>'PRESTAMO '!D8,0,IF(I58>'PRESTAMO '!$E$17,'PRESTAMO '!$E$17,IMPUESTOS!I58)) -> 8.3702892e+08 | J60: =IF(I6>'PRESTAMO '!D8,0,IF(J58>'PRESTAMO '!$E$18,'PRESTAMO '!$E$18,IMPUESTOS!J58)) -> 4.355762e+08 | K60: =IF(J6>'PRESTAMO '!D8,0,IF(K58>'PRESTAMO '!$E$19,'PRESTAMO '!$E$19,IMPUESTOS!K58)) -> 0 | L60: =IF(K6>'PRESTAMO '!D8,0,IF(L58>'PRESTAMO '!$E$20,'PRESTAMO '!$E$20,IMPUESTOS!L58)) -> 0 | M60: =IF(L6>'PRESTAMO '!D8,0,IF(M58>'PRESTAMO '!$E$21,'PRESTAMO '!$E$21,IMPUESTOS!M58)) -> 0 | N60: =IF(M6>'PRESTAMO '!D8,0,IF(N58>'PRESTAMO '!$E$22,'PRESTAMO '!$E$22,IMPUESTOS!N58)) -> 0 | O60: =IF(N6>'PRESTAMO '!D8,0,IF(O58>'PRESTAMO '!$E$23,'PRESTAMO '!$E$23,IMPUESTOS!O58)) -> 0 | P60: =IF(O6>'PRESTAMO '!D8,0,IF(P58>'PRESTAMO '!$E$24,'PRESTAMO '!$E$24,IMPUESTOS!P58)) -> 0 | Q60: =IF(P6>'PRESTAMO '!D8,0,IF(Q58>'PRESTAMO '!$E$25,'PRESTAMO '!$E$25,IMPUESTOS!Q58)) -> 0 | R60: =IF(Q6>'PRESTAMO '!D8,0,IF(R58>'PRESTAMO '!$E$26,'PRESTAMO '!$E$26,IMPUESTOS!R58)) -> 0 | S60: =IF(R6>'PRESTAMO '!D8,0,IF(S58>'PRESTAMO '!$E$27,'PRESTAMO '!$E$27,IMPUESTOS!S58)) -> 0 | T60: =IF(S6>'PRESTAMO '!D8,0,IF(T58>'PRESTAMO '!$E$28,'PRESTAMO '!$E$28,IMPUESTOS!T58)) -> 0 | U60: =IF(T6>'PRESTAMO '!D8,0,IF(U58>'PRESTAMO '!$E$29,'PRESTAMO '!$E$29,IMPUESTOS!U58)) -> 0 | V60: =IF(U6>'PRESTAMO '!D8,0,IF(V58>'PRESTAMO '!$E$30,'PRESTAMO '!$E$30,IMPUESTOS!V58)) -> 0 | W60: =IF(V6>'PRESTAMO '!D8,0,IF(W58>'PRESTAMO '!$E$31,'PRESTAMO '!$E$31,IMPUESTOS!W58)) -> 0 | X60: =SUM(D60:W60) -> 8.0420584e+09
B62: BASE IMPONIBLE | D62: =+D56-D60-D48 -> -6.6040712e+09 | E62: =+E56-E60-E48 -> 1.8157542e+10 | F62: =+F56-F60-F48 -> 1.6540701e+10 | G62: =+G56-G60-G48 -> 1.2775498e+10 | H62: =+H56-H60-H48 -> 1.2568442e+10 | I62: =+I56-I60-I48 -> 1.2609524e+10 | J62: =+J56-J60-J48 -> 1.2897209e+10 | K62: =+K56-K60-K48 -> 1.3166409e+10 | ... W62: =+W56-W60-W48 -> 1.9706051e+10 | X62: =SUM(D62:W62) -> 3.1637773e+11
B64: B.I.ACUMULADA | D64: =IF((D62+C64)>0,0,(D62+C64)) -> -6.6040712e+09 | E64: =IF((E62+D64)>0,0,(E62+D64)) -> 0 | F64: =IF((F62+E64)>0,0,(F62+E64)) -> 0 | G64: =IF((G62+F64)>0,0,(G62+F64)) -> 0 | H64: =IF((H62+G64)>0,0,(H62+G64)) -> 0 | I64: =IF((I62+H64)>0,0,(I62+H64)) -> 0 | J64: =IF((J62+I64)>0,0,(J62+I64)) -> 0 | K64: =IF((K62+J64)>0,0,(K62+J64)) -> 0 | ... W64: =IF((W62+V64)>0,0,(W62+V64)) -> 0 | X64: =SUM(D64:W64) -> -6.6040712e+09
B66: IMPUESTO A PAGAR | D66: =IF(D62<0,0,IF((D62+C64)<0,0,(D62+C64)*$AA$16)) -> 0 | E66: =IF(E62<0,0,IF((E62+D64)<0,0,(E62+D64)*$AA$16)) -> 4.0437148e+09 | F66: =IF(F62<0,0,IF((F62+E64)<0,0,(F62+E64)*$AA$16)) -> 5.7892452e+09 | G66: =IF(G62<0,0,IF((G62+F64)<0,0,(G62+F64)*$AA$16)) -> 4.4714244e+09 | H66: =IF(H62<0,0,IF((H62+G64)<0,0,(H62+G64)*$AA$16)) -> 4.3989546e+09 | I66: =IF(I62<0,0,IF((I62+H64)<0,0,(I62+H64)*$AA$16)) -> 4.4133335e+09 | J66: =IF(J62<0,0,IF((J62+I64)<0,0,(J62+I64)*$AA$16)) -> 4.514023e+09 | K66: =IF(K62<0,0,IF((K62+J64)<0,0,(K62+J64)*$AA$16)) -> 4.6082432e+09 | ... W66: =IF(W62<0,0,IF((W62+V64)<0,0,(W62+V64)*$AA$16)) -> 6.8971179e+09 | X66: =SUM(D66:W66) -> 1.1073221e+11
